[
  {
    "id": "153604003",
    "level": 4,
    "level_name": {
      "local": "Barangay",
      "en": "Barangay"
    },
    "name": {
      "local": "Bagoaingud",
      "en": "Bagoaingud",
      "slug": "bagoaingud-153604003"
    },
    "code": {
      "id": "153604003",
      "iso": null
    },
    "parent": {
      "id": "153604",
      "level": 3,
      "name": {
        "local": "Bayang",
        "en": "Bayang",
        "slug": "bayang-153604"
      }
    },
    "ancestors": [
      {
        "id": "ARMM",
        "level": 1,
        "name": {
          "local": "Autonomous Region in Muslim Mindanao",
          "en": "Autonomous Region in Muslim Mindanao",
          "slug": "autonomous-region-in-muslim-mindanao-ARMM"
        }
      },
      {
        "id": "153600",
        "level": 2,
        "name": {
          "local": "Lanao del Sur",
          "en": "Lanao del Sur",
          "slug": "lanao-del-sur-153600"
        }
      },
      {
        "id": "153604",
        "level": 3,
        "name": {
          "local": "Bayang",
          "en": "Bayang",
          "slug": "bayang-153604"
        }
      }
    ],
    "children_count": {},
    "zip_codes": [
      "9309"
    ],
    "geo": {
      "lat": "7.79306",
      "lon": "124.19194"
    },
    "metadata": {},
    "source": {}
  },
  {
    "id": "153604004",
    "level": 4,
    "level_name": {
      "local": "Barangay",
      "en": "Barangay"
    },
    "name": {
      "local": "Bairan (Pob.)",
      "en": "Bairan (Pob.)",
      "slug": "bairan-pob-153604004"
    },
    "code": {
      "id": "153604004",
      "iso": null
    },
    "parent": {
      "id": "153604",
      "level": 3,
      "name": {
        "local": "Bayang",
        "en": "Bayang",
        "slug": "bayang-153604"
      }
    },
    "ancestors": [
      {
        "id": "ARMM",
        "level": 1,
        "name": {
          "local": "Autonomous Region in Muslim Mindanao",
          "en": "Autonomous Region in Muslim Mindanao",
          "slug": "autonomous-region-in-muslim-mindanao-ARMM"
        }
      },
      {
        "id": "153600",
        "level": 2,
        "name": {
          "local": "Lanao del Sur",
          "en": "Lanao del Sur",
          "slug": "lanao-del-sur-153600"
        }
      },
      {
        "id": "153604",
        "level": 3,
        "name": {
          "local": "Bayang",
          "en": "Bayang",
          "slug": "bayang-153604"
        }
      }
    ],
    "children_count": {},
    "zip_codes": [
      "9309"
    ],
    "geo": {
      "lat": "7.8",
      "lon": "124.2167"
    },
    "metadata": {},
    "source": {}
  },
  {
    "id": "153604005",
    "level": 4,
    "level_name": {
      "local": "Barangay",
      "en": "Barangay"
    },
    "name": {
      "local": "Bandingun",
      "en": "Bandingun",
      "slug": "bandingun-153604005"
    },
    "code": {
      "id": "153604005",
      "iso": null
    },
    "parent": {
      "id": "153604",
      "level": 3,
      "name": {
        "local": "Bayang",
        "en": "Bayang",
        "slug": "bayang-153604"
      }
    },
    "ancestors": [
      {
        "id": "ARMM",
        "level": 1,
        "name": {
          "local": "Autonomous Region in Muslim Mindanao",
          "en": "Autonomous Region in Muslim Mindanao",
          "slug": "autonomous-region-in-muslim-mindanao-ARMM"
        }
      },
      {
        "id": "153600",
        "level": 2,
        "name": {
          "local": "Lanao del Sur",
          "en": "Lanao del Sur",
          "slug": "lanao-del-sur-153600"
        }
      },
      {
        "id": "153604",
        "level": 3,
        "name": {
          "local": "Bayang",
          "en": "Bayang",
          "slug": "bayang-153604"
        }
      }
    ],
    "children_count": {},
    "zip_codes": [
      "9309"
    ],
    "geo": {
      "lat": "7.79306",
      "lon": "124.19194"
    },
    "metadata": {},
    "source": {}
  },
  {
    "id": "153604006",
    "level": 4,
    "level_name": {
      "local": "Barangay",
      "en": "Barangay"
    },
    "name": {
      "local": "Biabi",
      "en": "Biabi",
      "slug": "biabi-153604006"
    },
    "code": {
      "id": "153604006",
      "iso": null
    },
    "parent": {
      "id": "153604",
      "level": 3,
      "name": {
        "local": "Bayang",
        "en": "Bayang",
        "slug": "bayang-153604"
      }
    },
    "ancestors": [
      {
        "id": "ARMM",
        "level": 1,
        "name": {
          "local": "Autonomous Region in Muslim Mindanao",
          "en": "Autonomous Region in Muslim Mindanao",
          "slug": "autonomous-region-in-muslim-mindanao-ARMM"
        }
      },
      {
        "id": "153600",
        "level": 2,
        "name": {
          "local": "Lanao del Sur",
          "en": "Lanao del Sur",
          "slug": "lanao-del-sur-153600"
        }
      },
      {
        "id": "153604",
        "level": 3,
        "name": {
          "local": "Bayang",
          "en": "Bayang",
          "slug": "bayang-153604"
        }
      }
    ],
    "children_count": {},
    "zip_codes": [
      "9309"
    ],
    "geo": {
      "lat": "7.8",
      "lon": "124.2167"
    },
    "metadata": {},
    "source": {}
  },
  {
    "id": "153604007",
    "level": 4,
    "level_name": {
      "local": "Barangay",
      "en": "Barangay"
    },
    "name": {
      "local": "Bialaan",
      "en": "Bialaan",
      "slug": "bialaan-153604007"
    },
    "code": {
      "id": "153604007",
      "iso": null
    },
    "parent": {
      "id": "153604",
      "level": 3,
      "name": {
        "local": "Bayang",
        "en": "Bayang",
        "slug": "bayang-153604"
      }
    },
    "ancestors": [
      {
        "id": "ARMM",
        "level": 1,
        "name": {
          "local": "Autonomous Region in Muslim Mindanao",
          "en": "Autonomous Region in Muslim Mindanao",
          "slug": "autonomous-region-in-muslim-mindanao-ARMM"
        }
      },
      {
        "id": "153600",
        "level": 2,
        "name": {
          "local": "Lanao del Sur",
          "en": "Lanao del Sur",
          "slug": "lanao-del-sur-153600"
        }
      },
      {
        "id": "153604",
        "level": 3,
        "name": {
          "local": "Bayang",
          "en": "Bayang",
          "slug": "bayang-153604"
        }
      }
    ],
    "children_count": {},
    "zip_codes": [
      "9309"
    ],
    "geo": {
      "lat": "7.79306",
      "lon": "124.19194"
    },
    "metadata": {},
    "source": {}
  },
  {
    "id": "153604017",
    "level": 4,
    "level_name": {
      "local": "Barangay",
      "en": "Barangay"
    },
    "name": {
      "local": "Bubong Lilod",
      "en": "Bubong Lilod",
      "slug": "bubong-lilod-153604017"
    },
    "code": {
      "id": "153604017",
      "iso": null
    },
    "parent": {
      "id": "153604",
      "level": 3,
      "name": {
        "local": "Bayang",
        "en": "Bayang",
        "slug": "bayang-153604"
      }
    },
    "ancestors": [
      {
        "id": "ARMM",
        "level": 1,
        "name": {
          "local": "Autonomous Region in Muslim Mindanao",
          "en": "Autonomous Region in Muslim Mindanao",
          "slug": "autonomous-region-in-muslim-mindanao-ARMM"
        }
      },
      {
        "id": "153600",
        "level": 2,
        "name": {
          "local": "Lanao del Sur",
          "en": "Lanao del Sur",
          "slug": "lanao-del-sur-153600"
        }
      },
      {
        "id": "153604",
        "level": 3,
        "name": {
          "local": "Bayang",
          "en": "Bayang",
          "slug": "bayang-153604"
        }
      }
    ],
    "children_count": {},
    "zip_codes": [
      "9309"
    ],
    "geo": {
      "lat": "8.02",
      "lon": "124.48"
    },
    "metadata": {},
    "source": {}
  },
  {
    "id": "153604055",
    "level": 4,
    "level_name": {
      "local": "Barangay",
      "en": "Barangay"
    },
    "name": {
      "local": "Bubong Raya",
      "en": "Bubong Raya",
      "slug": "bubong-raya-153604055"
    },
    "code": {
      "id": "153604055",
      "iso": null
    },
    "parent": {
      "id": "153604",
      "level": 3,
      "name": {
        "local": "Bayang",
        "en": "Bayang",
        "slug": "bayang-153604"
      }
    },
    "ancestors": [
      {
        "id": "ARMM",
        "level": 1,
        "name": {
          "local": "Autonomous Region in Muslim Mindanao",
          "en": "Autonomous Region in Muslim Mindanao",
          "slug": "autonomous-region-in-muslim-mindanao-ARMM"
        }
      },
      {
        "id": "153600",
        "level": 2,
        "name": {
          "local": "Lanao del Sur",
          "en": "Lanao del Sur",
          "slug": "lanao-del-sur-153600"
        }
      },
      {
        "id": "153604",
        "level": 3,
        "name": {
          "local": "Bayang",
          "en": "Bayang",
          "slug": "bayang-153604"
        }
      }
    ],
    "children_count": {},
    "zip_codes": [
      "9309"
    ],
    "geo": {
      "lat": "8.02",
      "lon": "124.48"
    },
    "metadata": {},
    "source": {}
  },
  {
    "id": "153604009",
    "level": 4,
    "level_name": {
      "local": "Barangay",
      "en": "Barangay"
    },
    "name": {
      "local": "Cadayonan",
      "en": "Cadayonan",
      "slug": "cadayonan-153604009"
    },
    "code": {
      "id": "153604009",
      "iso": null
    },
    "parent": {
      "id": "153604",
      "level": 3,
      "name": {
        "local": "Bayang",
        "en": "Bayang",
        "slug": "bayang-153604"
      }
    },
    "ancestors": [
      {
        "id": "ARMM",
        "level": 1,
        "name": {
          "local": "Autonomous Region in Muslim Mindanao",
          "en": "Autonomous Region in Muslim Mindanao",
          "slug": "autonomous-region-in-muslim-mindanao-ARMM"
        }
      },
      {
        "id": "153600",
        "level": 2,
        "name": {
          "local": "Lanao del Sur",
          "en": "Lanao del Sur",
          "slug": "lanao-del-sur-153600"
        }
      },
      {
        "id": "153604",
        "level": 3,
        "name": {
          "local": "Bayang",
          "en": "Bayang",
          "slug": "bayang-153604"
        }
      }
    ],
    "children_count": {},
    "zip_codes": [
      "9309"
    ],
    "geo": {
      "lat": "7.8503",
      "lon": "124.3306"
    },
    "metadata": {},
    "source": {}
  },
  {
    "id": "153604027",
    "level": 4,
    "level_name": {
      "local": "Barangay",
      "en": "Barangay"
    },
    "name": {
      "local": "Cadingilan Occidental",
      "en": "Cadingilan Occidental",
      "slug": "cadingilan-occidental-153604027"
    },
    "code": {
      "id": "153604027",
      "iso": null
    },
    "parent": {
      "id": "153604",
      "level": 3,
      "name": {
        "local": "Bayang",
        "en": "Bayang",
        "slug": "bayang-153604"
      }
    },
    "ancestors": [
      {
        "id": "ARMM",
        "level": 1,
        "name": {
          "local": "Autonomous Region in Muslim Mindanao",
          "en": "Autonomous Region in Muslim Mindanao",
          "slug": "autonomous-region-in-muslim-mindanao-ARMM"
        }
      },
      {
        "id": "153600",
        "level": 2,
        "name": {
          "local": "Lanao del Sur",
          "en": "Lanao del Sur",
          "slug": "lanao-del-sur-153600"
        }
      },
      {
        "id": "153604",
        "level": 3,
        "name": {
          "local": "Bayang",
          "en": "Bayang",
          "slug": "bayang-153604"
        }
      }
    ],
    "children_count": {},
    "zip_codes": [
      "9309"
    ],
    "geo": {
      "lat": "7.75",
      "lon": "124.2"
    },
    "metadata": {},
    "source": {}
  },
  {
    "id": "153604028",
    "level": 4,
    "level_name": {
      "local": "Barangay",
      "en": "Barangay"
    },
    "name": {
      "local": "Cadingilan Oriental",
      "en": "Cadingilan Oriental",
      "slug": "cadingilan-oriental-153604028"
    },
    "code": {
      "id": "153604028",
      "iso": null
    },
    "parent": {
      "id": "153604",
      "level": 3,
      "name": {
        "local": "Bayang",
        "en": "Bayang",
        "slug": "bayang-153604"
      }
    },
    "ancestors": [
      {
        "id": "ARMM",
        "level": 1,
        "name": {
          "local": "Autonomous Region in Muslim Mindanao",
          "en": "Autonomous Region in Muslim Mindanao",
          "slug": "autonomous-region-in-muslim-mindanao-ARMM"
        }
      },
      {
        "id": "153600",
        "level": 2,
        "name": {
          "local": "Lanao del Sur",
          "en": "Lanao del Sur",
          "slug": "lanao-del-sur-153600"
        }
      },
      {
        "id": "153604",
        "level": 3,
        "name": {
          "local": "Bayang",
          "en": "Bayang",
          "slug": "bayang-153604"
        }
      }
    ],
    "children_count": {},
    "zip_codes": [
      "9309"
    ],
    "geo": {
      "lat": "7.75",
      "lon": "124.2"
    },
    "metadata": {},
    "source": {}
  },
  {
    "id": "153604012",
    "level": 4,
    "level_name": {
      "local": "Barangay",
      "en": "Barangay"
    },
    "name": {
      "local": "Condaraan Pob. (Condaraan Dimadap)",
      "en": "Condaraan Pob. (Condaraan Dimadap)",
      "slug": "condaraan-pob-condaraan-dimadap-153604012"
    },
    "code": {
      "id": "153604012",
      "iso": null
    },
    "parent": {
      "id": "153604",
      "level": 3,
      "name": {
        "local": "Bayang",
        "en": "Bayang",
        "slug": "bayang-153604"
      }
    },
    "ancestors": [
      {
        "id": "ARMM",
        "level": 1,
        "name": {
          "local": "Autonomous Region in Muslim Mindanao",
          "en": "Autonomous Region in Muslim Mindanao",
          "slug": "autonomous-region-in-muslim-mindanao-ARMM"
        }
      },
      {
        "id": "153600",
        "level": 2,
        "name": {
          "local": "Lanao del Sur",
          "en": "Lanao del Sur",
          "slug": "lanao-del-sur-153600"
        }
      },
      {
        "id": "153604",
        "level": 3,
        "name": {
          "local": "Bayang",
          "en": "Bayang",
          "slug": "bayang-153604"
        }
      }
    ],
    "children_count": {},
    "zip_codes": [
      "9309"
    ],
    "geo": {
      "lat": "7.79306",
      "lon": "124.19194"
    },
    "metadata": {},
    "source": {}
  },
  {
    "id": "153604013",
    "level": 4,
    "level_name": {
      "local": "Barangay",
      "en": "Barangay"
    },
    "name": {
      "local": "Cormatan",
      "en": "Cormatan",
      "slug": "cormatan-153604013"
    },
    "code": {
      "id": "153604013",
      "iso": null
    },
    "parent": {
      "id": "153604",
      "level": 3,
      "name": {
        "local": "Bayang",
        "en": "Bayang",
        "slug": "bayang-153604"
      }
    },
    "ancestors": [
      {
        "id": "ARMM",
        "level": 1,
        "name": {
          "local": "Autonomous Region in Muslim Mindanao",
          "en": "Autonomous Region in Muslim Mindanao",
          "slug": "autonomous-region-in-muslim-mindanao-ARMM"
        }
      },
      {
        "id": "153600",
        "level": 2,
        "name": {
          "local": "Lanao del Sur",
          "en": "Lanao del Sur",
          "slug": "lanao-del-sur-153600"
        }
      },
      {
        "id": "153604",
        "level": 3,
        "name": {
          "local": "Bayang",
          "en": "Bayang",
          "slug": "bayang-153604"
        }
      }
    ],
    "children_count": {},
    "zip_codes": [
      "9309"
    ],
    "geo": {
      "lat": "7.79306",
      "lon": "124.19194"
    },
    "metadata": {},
    "source": {}
  },
  {
    "id": "153604054",
    "level": 4,
    "level_name": {
      "local": "Barangay",
      "en": "Barangay"
    },
    "name": {
      "local": "Gandamato",
      "en": "Gandamato",
      "slug": "gandamato-153604054"
    },
    "code": {
      "id": "153604054",
      "iso": null
    },
    "parent": {
      "id": "153604",
      "level": 3,
      "name": {
        "local": "Bayang",
        "en": "Bayang",
        "slug": "bayang-153604"
      }
    },
    "ancestors": [
      {
        "id": "ARMM",
        "level": 1,
        "name": {
          "local": "Autonomous Region in Muslim Mindanao",
          "en": "Autonomous Region in Muslim Mindanao",
          "slug": "autonomous-region-in-muslim-mindanao-ARMM"
        }
      },
      {
        "id": "153600",
        "level": 2,
        "name": {
          "local": "Lanao del Sur",
          "en": "Lanao del Sur",
          "slug": "lanao-del-sur-153600"
        }
      },
      {
        "id": "153604",
        "level": 3,
        "name": {
          "local": "Bayang",
          "en": "Bayang",
          "slug": "bayang-153604"
        }
      }
    ],
    "children_count": {},
    "zip_codes": [
      "9309"
    ],
    "geo": {
      "lat": "7.79306",
      "lon": "124.19194"
    },
    "metadata": {},
    "source": {}
  },
  {
    "id": "153604014",
    "level": 4,
    "level_name": {
      "local": "Barangay",
      "en": "Barangay"
    },
    "name": {
      "local": "Ilian",
      "en": "Ilian",
      "slug": "ilian-153604014"
    },
    "code": {
      "id": "153604014",
      "iso": null
    },
    "parent": {
      "id": "153604",
      "level": 3,
      "name": {
        "local": "Bayang",
        "en": "Bayang",
        "slug": "bayang-153604"
      }
    },
    "ancestors": [
      {
        "id": "ARMM",
        "level": 1,
        "name": {
          "local": "Autonomous Region in Muslim Mindanao",
          "en": "Autonomous Region in Muslim Mindanao",
          "slug": "autonomous-region-in-muslim-mindanao-ARMM"
        }
      },
      {
        "id": "153600",
        "level": 2,
        "name": {
          "local": "Lanao del Sur",
          "en": "Lanao del Sur",
          "slug": "lanao-del-sur-153600"
        }
      },
      {
        "id": "153604",
        "level": 3,
        "name": {
          "local": "Bayang",
          "en": "Bayang",
          "slug": "bayang-153604"
        }
      }
    ],
    "children_count": {},
    "zip_codes": [
      "9309"
    ],
    "geo": {
      "lat": "10.4071",
      "lon": "119.579"
    },
    "metadata": {},
    "source": {}
  },
  {
    "id": "153604011",
    "level": 4,
    "level_name": {
      "local": "Barangay",
      "en": "Barangay"
    },
    "name": {
      "local": "Lalapung Central",
      "en": "Lalapung Central",
      "slug": "lalapung-central-153604011"
    },
    "code": {
      "id": "153604011",
      "iso": null
    },
    "parent": {
      "id": "153604",
      "level": 3,
      "name": {
        "local": "Bayang",
        "en": "Bayang",
        "slug": "bayang-153604"
      }
    },
    "ancestors": [
      {
        "id": "ARMM",
        "level": 1,
        "name": {
          "local": "Autonomous Region in Muslim Mindanao",
          "en": "Autonomous Region in Muslim Mindanao",
          "slug": "autonomous-region-in-muslim-mindanao-ARMM"
        }
      },
      {
        "id": "153600",
        "level": 2,
        "name": {
          "local": "Lanao del Sur",
          "en": "Lanao del Sur",
          "slug": "lanao-del-sur-153600"
        }
      },
      {
        "id": "153604",
        "level": 3,
        "name": {
          "local": "Bayang",
          "en": "Bayang",
          "slug": "bayang-153604"
        }
      }
    ],
    "children_count": {},
    "zip_codes": [
      "9309"
    ],
    "geo": {
      "lat": "7.7808",
      "lon": "124.2201"
    },
    "metadata": {},
    "source": {}
  },
  {
    "id": "153604015",
    "level": 4,
    "level_name": {
      "local": "Barangay",
      "en": "Barangay"
    },
    "name": {
      "local": "Lalapung Proper (Pob.)",
      "en": "Lalapung Proper (Pob.)",
      "slug": "lalapung-proper-pob-153604015"
    },
    "code": {
      "id": "153604015",
      "iso": null
    },
    "parent": {
      "id": "153604",
      "level": 3,
      "name": {
        "local": "Bayang",
        "en": "Bayang",
        "slug": "bayang-153604"
      }
    },
    "ancestors": [
      {
        "id": "ARMM",
        "level": 1,
        "name": {
          "local": "Autonomous Region in Muslim Mindanao",
          "en": "Autonomous Region in Muslim Mindanao",
          "slug": "autonomous-region-in-muslim-mindanao-ARMM"
        }
      },
      {
        "id": "153600",
        "level": 2,
        "name": {
          "local": "Lanao del Sur",
          "en": "Lanao del Sur",
          "slug": "lanao-del-sur-153600"
        }
      },
      {
        "id": "153604",
        "level": 3,
        "name": {
          "local": "Bayang",
          "en": "Bayang",
          "slug": "bayang-153604"
        }
      }
    ],
    "children_count": {},
    "zip_codes": [
      "9309"
    ],
    "geo": {
      "lat": "7.7808",
      "lon": "124.2201"
    },
    "metadata": {},
    "source": {}
  },
  {
    "id": "153604053",
    "level": 4,
    "level_name": {
      "local": "Barangay",
      "en": "Barangay"
    },
    "name": {
      "local": "Lalapung Upper",
      "en": "Lalapung Upper",
      "slug": "lalapung-upper-153604053"
    },
    "code": {
      "id": "153604053",
      "iso": null
    },
    "parent": {
      "id": "153604",
      "level": 3,
      "name": {
        "local": "Bayang",
        "en": "Bayang",
        "slug": "bayang-153604"
      }
    },
    "ancestors": [
      {
        "id": "ARMM",
        "level": 1,
        "name": {
          "local": "Autonomous Region in Muslim Mindanao",
          "en": "Autonomous Region in Muslim Mindanao",
          "slug": "autonomous-region-in-muslim-mindanao-ARMM"
        }
      },
      {
        "id": "153600",
        "level": 2,
        "name": {
          "local": "Lanao del Sur",
          "en": "Lanao del Sur",
          "slug": "lanao-del-sur-153600"
        }
      },
      {
        "id": "153604",
        "level": 3,
        "name": {
          "local": "Bayang",
          "en": "Bayang",
          "slug": "bayang-153604"
        }
      }
    ],
    "children_count": {},
    "zip_codes": [
      "9309"
    ],
    "geo": {
      "lat": "7.7808",
      "lon": "124.2201"
    },
    "metadata": {},
    "source": {}
  },
  {
    "id": "153604018",
    "level": 4,
    "level_name": {
      "local": "Barangay",
      "en": "Barangay"
    },
    "name": {
      "local": "Linao",
      "en": "Linao",
      "slug": "linao-153604018"
    },
    "code": {
      "id": "153604018",
      "iso": null
    },
    "parent": {
      "id": "153604",
      "level": 3,
      "name": {
        "local": "Bayang",
        "en": "Bayang",
        "slug": "bayang-153604"
      }
    },
    "ancestors": [
      {
        "id": "ARMM",
        "level": 1,
        "name": {
          "local": "Autonomous Region in Muslim Mindanao",
          "en": "Autonomous Region in Muslim Mindanao",
          "slug": "autonomous-region-in-muslim-mindanao-ARMM"
        }
      },
      {
        "id": "153600",
        "level": 2,
        "name": {
          "local": "Lanao del Sur",
          "en": "Lanao del Sur",
          "slug": "lanao-del-sur-153600"
        }
      },
      {
        "id": "153604",
        "level": 3,
        "name": {
          "local": "Bayang",
          "en": "Bayang",
          "slug": "bayang-153604"
        }
      }
    ],
    "children_count": {},
    "zip_codes": [
      "9309"
    ],
    "geo": {
      "lat": "6.0294",
      "lon": "124.5125"
    },
    "metadata": {},
    "source": {}
  },
  {
    "id": "153604019",
    "level": 4,
    "level_name": {
      "local": "Barangay",
      "en": "Barangay"
    },
    "name": {
      "local": "Linuk (Pob.)",
      "en": "Linuk (Pob.)",
      "slug": "linuk-pob-153604019"
    },
    "code": {
      "id": "153604019",
      "iso": null
    },
    "parent": {
      "id": "153604",
      "level": 3,
      "name": {
        "local": "Bayang",
        "en": "Bayang",
        "slug": "bayang-153604"
      }
    },
    "ancestors": [
      {
        "id": "ARMM",
        "level": 1,
        "name": {
          "local": "Autonomous Region in Muslim Mindanao",
          "en": "Autonomous Region in Muslim Mindanao",
          "slug": "autonomous-region-in-muslim-mindanao-ARMM"
        }
      },
      {
        "id": "153600",
        "level": 2,
        "name": {
          "local": "Lanao del Sur",
          "en": "Lanao del Sur",
          "slug": "lanao-del-sur-153600"
        }
      },
      {
        "id": "153604",
        "level": 3,
        "name": {
          "local": "Bayang",
          "en": "Bayang",
          "slug": "bayang-153604"
        }
      }
    ],
    "children_count": {},
    "zip_codes": [
      "9309"
    ],
    "geo": {
      "lat": "7.8767",
      "lon": "124.3242"
    },
    "metadata": {},
    "source": {}
  },
  {
    "id": "153604020",
    "level": 4,
    "level_name": {
      "local": "Barangay",
      "en": "Barangay"
    },
    "name": {
      "local": "Liong",
      "en": "Liong",
      "slug": "liong-153604020"
    },
    "code": {
      "id": "153604020",
      "iso": null
    },
    "parent": {
      "id": "153604",
      "level": 3,
      "name": {
        "local": "Bayang",
        "en": "Bayang",
        "slug": "bayang-153604"
      }
    },
    "ancestors": [
      {
        "id": "ARMM",
        "level": 1,
        "name": {
          "local": "Autonomous Region in Muslim Mindanao",
          "en": "Autonomous Region in Muslim Mindanao",
          "slug": "autonomous-region-in-muslim-mindanao-ARMM"
        }
      },
      {
        "id": "153600",
        "level": 2,
        "name": {
          "local": "Lanao del Sur",
          "en": "Lanao del Sur",
          "slug": "lanao-del-sur-153600"
        }
      },
      {
        "id": "153604",
        "level": 3,
        "name": {
          "local": "Bayang",
          "en": "Bayang",
          "slug": "bayang-153604"
        }
      }
    ],
    "children_count": {},
    "zip_codes": [
      "9309"
    ],
    "geo": {
      "lat": "7.4542",
      "lon": "124.6517"
    },
    "metadata": {},
    "source": {}
  },
  {
    "id": "153604021",
    "level": 4,
    "level_name": {
      "local": "Barangay",
      "en": "Barangay"
    },
    "name": {
      "local": "Lumbac",
      "en": "Lumbac",
      "slug": "lumbac-153604021"
    },
    "code": {
      "id": "153604021",
      "iso": null
    },
    "parent": {
      "id": "153604",
      "level": 3,
      "name": {
        "local": "Bayang",
        "en": "Bayang",
        "slug": "bayang-153604"
      }
    },
    "ancestors": [
      {
        "id": "ARMM",
        "level": 1,
        "name": {
          "local": "Autonomous Region in Muslim Mindanao",
          "en": "Autonomous Region in Muslim Mindanao",
          "slug": "autonomous-region-in-muslim-mindanao-ARMM"
        }
      },
      {
        "id": "153600",
        "level": 2,
        "name": {
          "local": "Lanao del Sur",
          "en": "Lanao del Sur",
          "slug": "lanao-del-sur-153600"
        }
      },
      {
        "id": "153604",
        "level": 3,
        "name": {
          "local": "Bayang",
          "en": "Bayang",
          "slug": "bayang-153604"
        }
      }
    ],
    "children_count": {},
    "zip_codes": [
      "9309"
    ],
    "geo": {
      "lat": "7.8678",
      "lon": "124.3683"
    },
    "metadata": {},
    "source": {}
  },
  {
    "id": "153604010",
    "level": 4,
    "level_name": {
      "local": "Barangay",
      "en": "Barangay"
    },
    "name": {
      "local": "Lumbac Cadayonan",
      "en": "Lumbac Cadayonan",
      "slug": "lumbac-cadayonan-153604010"
    },
    "code": {
      "id": "153604010",
      "iso": null
    },
    "parent": {
      "id": "153604",
      "level": 3,
      "name": {
        "local": "Bayang",
        "en": "Bayang",
        "slug": "bayang-153604"
      }
    },
    "ancestors": [
      {
        "id": "ARMM",
        "level": 1,
        "name": {
          "local": "Autonomous Region in Muslim Mindanao",
          "en": "Autonomous Region in Muslim Mindanao",
          "slug": "autonomous-region-in-muslim-mindanao-ARMM"
        }
      },
      {
        "id": "153600",
        "level": 2,
        "name": {
          "local": "Lanao del Sur",
          "en": "Lanao del Sur",
          "slug": "lanao-del-sur-153600"
        }
      },
      {
        "id": "153604",
        "level": 3,
        "name": {
          "local": "Bayang",
          "en": "Bayang",
          "slug": "bayang-153604"
        }
      }
    ],
    "children_count": {},
    "zip_codes": [
      "9309"
    ],
    "geo": {
      "lat": "7.8678",
      "lon": "124.3683"
    },
    "metadata": {},
    "source": {}
  },
  {
    "id": "153604024",
    "level": 4,
    "level_name": {
      "local": "Barangay",
      "en": "Barangay"
    },
    "name": {
      "local": "Maliwanag",
      "en": "Maliwanag",
      "slug": "maliwanag-153604024"
    },
    "code": {
      "id": "153604024",
      "iso": null
    },
    "parent": {
      "id": "153604",
      "level": 3,
      "name": {
        "local": "Bayang",
        "en": "Bayang",
        "slug": "bayang-153604"
      }
    },
    "ancestors": [
      {
        "id": "ARMM",
        "level": 1,
        "name": {
          "local": "Autonomous Region in Muslim Mindanao",
          "en": "Autonomous Region in Muslim Mindanao",
          "slug": "autonomous-region-in-muslim-mindanao-ARMM"
        }
      },
      {
        "id": "153600",
        "level": 2,
        "name": {
          "local": "Lanao del Sur",
          "en": "Lanao del Sur",
          "slug": "lanao-del-sur-153600"
        }
      },
      {
        "id": "153604",
        "level": 3,
        "name": {
          "local": "Bayang",
          "en": "Bayang",
          "slug": "bayang-153604"
        }
      }
    ],
    "children_count": {},
    "zip_codes": [
      "9309"
    ],
    "geo": {
      "lat": "7.79306",
      "lon": "124.19194"
    },
    "metadata": {},
    "source": {}
  },
  {
    "id": "153604025",
    "level": 4,
    "level_name": {
      "local": "Barangay",
      "en": "Barangay"
    },
    "name": {
      "local": "Mapantao",
      "en": "Mapantao",
      "slug": "mapantao-153604025"
    },
    "code": {
      "id": "153604025",
      "iso": null
    },
    "parent": {
      "id": "153604",
      "level": 3,
      "name": {
        "local": "Bayang",
        "en": "Bayang",
        "slug": "bayang-153604"
      }
    },
    "ancestors": [
      {
        "id": "ARMM",
        "level": 1,
        "name": {
          "local": "Autonomous Region in Muslim Mindanao",
          "en": "Autonomous Region in Muslim Mindanao",
          "slug": "autonomous-region-in-muslim-mindanao-ARMM"
        }
      },
      {
        "id": "153600",
        "level": 2,
        "name": {
          "local": "Lanao del Sur",
          "en": "Lanao del Sur",
          "slug": "lanao-del-sur-153600"
        }
      },
      {
        "id": "153604",
        "level": 3,
        "name": {
          "local": "Bayang",
          "en": "Bayang",
          "slug": "bayang-153604"
        }
      }
    ],
    "children_count": {},
    "zip_codes": [
      "9309"
    ],
    "geo": {
      "lat": "7.8422",
      "lon": "124.3747"
    },
    "metadata": {},
    "source": {}
  },
  {
    "id": "153604022",
    "level": 4,
    "level_name": {
      "local": "Barangay",
      "en": "Barangay"
    },
    "name": {
      "local": "Mimbalawag",
      "en": "Mimbalawag",
      "slug": "mimbalawag-153604022"
    },
    "code": {
      "id": "153604022",
      "iso": null
    },
    "parent": {
      "id": "153604",
      "level": 3,
      "name": {
        "local": "Bayang",
        "en": "Bayang",
        "slug": "bayang-153604"
      }
    },
    "ancestors": [
      {
        "id": "ARMM",
        "level": 1,
        "name": {
          "local": "Autonomous Region in Muslim Mindanao",
          "en": "Autonomous Region in Muslim Mindanao",
          "slug": "autonomous-region-in-muslim-mindanao-ARMM"
        }
      },
      {
        "id": "153600",
        "level": 2,
        "name": {
          "local": "Lanao del Sur",
          "en": "Lanao del Sur",
          "slug": "lanao-del-sur-153600"
        }
      },
      {
        "id": "153604",
        "level": 3,
        "name": {
          "local": "Bayang",
          "en": "Bayang",
          "slug": "bayang-153604"
        }
      }
    ],
    "children_count": {},
    "zip_codes": [
      "9309"
    ],
    "geo": {
      "lat": "7.79306",
      "lon": "124.19194"
    },
    "metadata": {},
    "source": {}
  },
  {
    "id": "153604030",
    "level": 4,
    "level_name": {
      "local": "Barangay",
      "en": "Barangay"
    },
    "name": {
      "local": "Palao",
      "en": "Palao",
      "slug": "palao-153604030"
    },
    "code": {
      "id": "153604030",
      "iso": null
    },
    "parent": {
      "id": "153604",
      "level": 3,
      "name": {
        "local": "Bayang",
        "en": "Bayang",
        "slug": "bayang-153604"
      }
    },
    "ancestors": [
      {
        "id": "ARMM",
        "level": 1,
        "name": {
          "local": "Autonomous Region in Muslim Mindanao",
          "en": "Autonomous Region in Muslim Mindanao",
          "slug": "autonomous-region-in-muslim-mindanao-ARMM"
        }
      },
      {
        "id": "153600",
        "level": 2,
        "name": {
          "local": "Lanao del Sur",
          "en": "Lanao del Sur",
          "slug": "lanao-del-sur-153600"
        }
      },
      {
        "id": "153604",
        "level": 3,
        "name": {
          "local": "Bayang",
          "en": "Bayang",
          "slug": "bayang-153604"
        }
      }
    ],
    "children_count": {},
    "zip_codes": [
      "9309"
    ],
    "geo": {
      "lat": "7.7704",
      "lon": "124.2057"
    },
    "metadata": {},
    "source": {}
  },
  {
    "id": "153604031",
    "level": 4,
    "level_name": {
      "local": "Barangay",
      "en": "Barangay"
    },
    "name": {
      "local": "Pama-an",
      "en": "Pama-an",
      "slug": "pama-an-153604031"
    },
    "code": {
      "id": "153604031",
      "iso": null
    },
    "parent": {
      "id": "153604",
      "level": 3,
      "name": {
        "local": "Bayang",
        "en": "Bayang",
        "slug": "bayang-153604"
      }
    },
    "ancestors": [
      {
        "id": "ARMM",
        "level": 1,
        "name": {
          "local": "Autonomous Region in Muslim Mindanao",
          "en": "Autonomous Region in Muslim Mindanao",
          "slug": "autonomous-region-in-muslim-mindanao-ARMM"
        }
      },
      {
        "id": "153600",
        "level": 2,
        "name": {
          "local": "Lanao del Sur",
          "en": "Lanao del Sur",
          "slug": "lanao-del-sur-153600"
        }
      },
      {
        "id": "153604",
        "level": 3,
        "name": {
          "local": "Bayang",
          "en": "Bayang",
          "slug": "bayang-153604"
        }
      }
    ],
    "children_count": {},
    "zip_codes": [
      "9309"
    ],
    "geo": {
      "lat": "7.79306",
      "lon": "124.19194"
    },
    "metadata": {},
    "source": {}
  },
  {
    "id": "153604032",
    "level": 4,
    "level_name": {
      "local": "Barangay",
      "en": "Barangay"
    },
    "name": {
      "local": "Pamacotan",
      "en": "Pamacotan",
      "slug": "pamacotan-153604032"
    },
    "code": {
      "id": "153604032",
      "iso": null
    },
    "parent": {
      "id": "153604",
      "level": 3,
      "name": {
        "local": "Bayang",
        "en": "Bayang",
        "slug": "bayang-153604"
      }
    },
    "ancestors": [
      {
        "id": "ARMM",
        "level": 1,
        "name": {
          "local": "Autonomous Region in Muslim Mindanao",
          "en": "Autonomous Region in Muslim Mindanao",
          "slug": "autonomous-region-in-muslim-mindanao-ARMM"
        }
      },
      {
        "id": "153600",
        "level": 2,
        "name": {
          "local": "Lanao del Sur",
          "en": "Lanao del Sur",
          "slug": "lanao-del-sur-153600"
        }
      },
      {
        "id": "153604",
        "level": 3,
        "name": {
          "local": "Bayang",
          "en": "Bayang",
          "slug": "bayang-153604"
        }
      }
    ],
    "children_count": {},
    "zip_codes": [
      "9309"
    ],
    "geo": {
      "lat": "7.79306",
      "lon": "124.19194"
    },
    "metadata": {},
    "source": {}
  },
  {
    "id": "153604033",
    "level": 4,
    "level_name": {
      "local": "Barangay",
      "en": "Barangay"
    },
    "name": {
      "local": "Pantar",
      "en": "Pantar",
      "slug": "pantar-153604033"
    },
    "code": {
      "id": "153604033",
      "iso": null
    },
    "parent": {
      "id": "153604",
      "level": 3,
      "name": {
        "local": "Bayang",
        "en": "Bayang",
        "slug": "bayang-153604"
      }
    },
    "ancestors": [
      {
        "id": "ARMM",
        "level": 1,
        "name": {
          "local": "Autonomous Region in Muslim Mindanao",
          "en": "Autonomous Region in Muslim Mindanao",
          "slug": "autonomous-region-in-muslim-mindanao-ARMM"
        }
      },
      {
        "id": "153600",
        "level": 2,
        "name": {
          "local": "Lanao del Sur",
          "en": "Lanao del Sur",
          "slug": "lanao-del-sur-153600"
        }
      },
      {
        "id": "153604",
        "level": 3,
        "name": {
          "local": "Bayang",
          "en": "Bayang",
          "slug": "bayang-153604"
        }
      }
    ],
    "children_count": {},
    "zip_codes": [
      "9309"
    ],
    "geo": {
      "lat": "8.0014",
      "lon": "124.1931"
    },
    "metadata": {},
    "source": {}
  },
  {
    "id": "153604034",
    "level": 4,
    "level_name": {
      "local": "Barangay",
      "en": "Barangay"
    },
    "name": {
      "local": "Parao",
      "en": "Parao",
      "slug": "parao-153604034"
    },
    "code": {
      "id": "153604034",
      "iso": null
    },
    "parent": {
      "id": "153604",
      "level": 3,
      "name": {
        "local": "Bayang",
        "en": "Bayang",
        "slug": "bayang-153604"
      }
    },
    "ancestors": [
      {
        "id": "ARMM",
        "level": 1,
        "name": {
          "local": "Autonomous Region in Muslim Mindanao",
          "en": "Autonomous Region in Muslim Mindanao",
          "slug": "autonomous-region-in-muslim-mindanao-ARMM"
        }
      },
      {
        "id": "153600",
        "level": 2,
        "name": {
          "local": "Lanao del Sur",
          "en": "Lanao del Sur",
          "slug": "lanao-del-sur-153600"
        }
      },
      {
        "id": "153604",
        "level": 3,
        "name": {
          "local": "Bayang",
          "en": "Bayang",
          "slug": "bayang-153604"
        }
      }
    ],
    "children_count": {},
    "zip_codes": [
      "9309"
    ],
    "geo": {
      "lat": "8.0864",
      "lon": "124.4058"
    },
    "metadata": {},
    "source": {}
  },
  {
    "id": "153604035",
    "level": 4,
    "level_name": {
      "local": "Barangay",
      "en": "Barangay"
    },
    "name": {
      "local": "Patong",
      "en": "Patong",
      "slug": "patong-153604035"
    },
    "code": {
      "id": "153604035",
      "iso": null
    },
    "parent": {
      "id": "153604",
      "level": 3,
      "name": {
        "local": "Bayang",
        "en": "Bayang",
        "slug": "bayang-153604"
      }
    },
    "ancestors": [
      {
        "id": "ARMM",
        "level": 1,
        "name": {
          "local": "Autonomous Region in Muslim Mindanao",
          "en": "Autonomous Region in Muslim Mindanao",
          "slug": "autonomous-region-in-muslim-mindanao-ARMM"
        }
      },
      {
        "id": "153600",
        "level": 2,
        "name": {
          "local": "Lanao del Sur",
          "en": "Lanao del Sur",
          "slug": "lanao-del-sur-153600"
        }
      },
      {
        "id": "153604",
        "level": 3,
        "name": {
          "local": "Bayang",
          "en": "Bayang",
          "slug": "bayang-153604"
        }
      }
    ],
    "children_count": {},
    "zip_codes": [
      "9309"
    ],
    "geo": {
      "lat": "11.6621",
      "lon": "124.993"
    },
    "metadata": {},
    "source": {}
  },
  {
    "id": "153604056",
    "level": 4,
    "level_name": {
      "local": "Barangay",
      "en": "Barangay"
    },
    "name": {
      "local": "Poblacion (Bayang)",
      "en": "Poblacion (Bayang)",
      "slug": "poblacion-bayang-153604056"
    },
    "code": {
      "id": "153604056",
      "iso": null
    },
    "parent": {
      "id": "153604",
      "level": 3,
      "name": {
        "local": "Bayang",
        "en": "Bayang",
        "slug": "bayang-153604"
      }
    },
    "ancestors": [
      {
        "id": "ARMM",
        "level": 1,
        "name": {
          "local": "Autonomous Region in Muslim Mindanao",
          "en": "Autonomous Region in Muslim Mindanao",
          "slug": "autonomous-region-in-muslim-mindanao-ARMM"
        }
      },
      {
        "id": "153600",
        "level": 2,
        "name": {
          "local": "Lanao del Sur",
          "en": "Lanao del Sur",
          "slug": "lanao-del-sur-153600"
        }
      },
      {
        "id": "153604",
        "level": 3,
        "name": {
          "local": "Bayang",
          "en": "Bayang",
          "slug": "bayang-153604"
        }
      }
    ],
    "children_count": {},
    "zip_codes": [
      "9309"
    ],
    "geo": {
      "lat": "14.33",
      "lon": "121.08"
    },
    "metadata": {},
    "source": {}
  },
  {
    "id": "153604036",
    "level": 4,
    "level_name": {
      "local": "Barangay",
      "en": "Barangay"
    },
    "name": {
      "local": "Porotan",
      "en": "Porotan",
      "slug": "porotan-153604036"
    },
    "code": {
      "id": "153604036",
      "iso": null
    },
    "parent": {
      "id": "153604",
      "level": 3,
      "name": {
        "local": "Bayang",
        "en": "Bayang",
        "slug": "bayang-153604"
      }
    },
    "ancestors": [
      {
        "id": "ARMM",
        "level": 1,
        "name": {
          "local": "Autonomous Region in Muslim Mindanao",
          "en": "Autonomous Region in Muslim Mindanao",
          "slug": "autonomous-region-in-muslim-mindanao-ARMM"
        }
      },
      {
        "id": "153600",
        "level": 2,
        "name": {
          "local": "Lanao del Sur",
          "en": "Lanao del Sur",
          "slug": "lanao-del-sur-153600"
        }
      },
      {
        "id": "153604",
        "level": 3,
        "name": {
          "local": "Bayang",
          "en": "Bayang",
          "slug": "bayang-153604"
        }
      }
    ],
    "children_count": {},
    "zip_codes": [
      "9309"
    ],
    "geo": {
      "lat": "12.3667",
      "lon": "124.5667"
    },
    "metadata": {},
    "source": {}
  },
  {
    "id": "153604037",
    "level": 4,
    "level_name": {
      "local": "Barangay",
      "en": "Barangay"
    },
    "name": {
      "local": "Rantian",
      "en": "Rantian",
      "slug": "rantian-153604037"
    },
    "code": {
      "id": "153604037",
      "iso": null
    },
    "parent": {
      "id": "153604",
      "level": 3,
      "name": {
        "local": "Bayang",
        "en": "Bayang",
        "slug": "bayang-153604"
      }
    },
    "ancestors": [
      {
        "id": "ARMM",
        "level": 1,
        "name": {
          "local": "Autonomous Region in Muslim Mindanao",
          "en": "Autonomous Region in Muslim Mindanao",
          "slug": "autonomous-region-in-muslim-mindanao-ARMM"
        }
      },
      {
        "id": "153600",
        "level": 2,
        "name": {
          "local": "Lanao del Sur",
          "en": "Lanao del Sur",
          "slug": "lanao-del-sur-153600"
        }
      },
      {
        "id": "153604",
        "level": 3,
        "name": {
          "local": "Bayang",
          "en": "Bayang",
          "slug": "bayang-153604"
        }
      }
    ],
    "children_count": {},
    "zip_codes": [
      "9309"
    ],
    "geo": {
      "lat": "7.7968",
      "lon": "124.1764"
    },
    "metadata": {},
    "source": {}
  },
  {
    "id": "153604038",
    "level": 4,
    "level_name": {
      "local": "Barangay",
      "en": "Barangay"
    },
    "name": {
      "local": "Raya Cadayonan",
      "en": "Raya Cadayonan",
      "slug": "raya-cadayonan-153604038"
    },
    "code": {
      "id": "153604038",
      "iso": null
    },
    "parent": {
      "id": "153604",
      "level": 3,
      "name": {
        "local": "Bayang",
        "en": "Bayang",
        "slug": "bayang-153604"
      }
    },
    "ancestors": [
      {
        "id": "ARMM",
        "level": 1,
        "name": {
          "local": "Autonomous Region in Muslim Mindanao",
          "en": "Autonomous Region in Muslim Mindanao",
          "slug": "autonomous-region-in-muslim-mindanao-ARMM"
        }
      },
      {
        "id": "153600",
        "level": 2,
        "name": {
          "local": "Lanao del Sur",
          "en": "Lanao del Sur",
          "slug": "lanao-del-sur-153600"
        }
      },
      {
        "id": "153604",
        "level": 3,
        "name": {
          "local": "Bayang",
          "en": "Bayang",
          "slug": "bayang-153604"
        }
      }
    ],
    "children_count": {},
    "zip_codes": [
      "9309"
    ],
    "geo": {
      "lat": "7.9167",
      "lon": "124.2"
    },
    "metadata": {},
    "source": {}
  },
  {
    "id": "153604039",
    "level": 4,
    "level_name": {
      "local": "Barangay",
      "en": "Barangay"
    },
    "name": {
      "local": "Rinabor (Pob.)",
      "en": "Rinabor (Pob.)",
      "slug": "rinabor-pob-153604039"
    },
    "code": {
      "id": "153604039",
      "iso": null
    },
    "parent": {
      "id": "153604",
      "level": 3,
      "name": {
        "local": "Bayang",
        "en": "Bayang",
        "slug": "bayang-153604"
      }
    },
    "ancestors": [
      {
        "id": "ARMM",
        "level": 1,
        "name": {
          "local": "Autonomous Region in Muslim Mindanao",
          "en": "Autonomous Region in Muslim Mindanao",
          "slug": "autonomous-region-in-muslim-mindanao-ARMM"
        }
      },
      {
        "id": "153600",
        "level": 2,
        "name": {
          "local": "Lanao del Sur",
          "en": "Lanao del Sur",
          "slug": "lanao-del-sur-153600"
        }
      },
      {
        "id": "153604",
        "level": 3,
        "name": {
          "local": "Bayang",
          "en": "Bayang",
          "slug": "bayang-153604"
        }
      }
    ],
    "children_count": {},
    "zip_codes": [
      "9309"
    ],
    "geo": {
      "lat": "7.79306",
      "lon": "124.19194"
    },
    "metadata": {},
    "source": {}
  },
  {
    "id": "153604041",
    "level": 4,
    "level_name": {
      "local": "Barangay",
      "en": "Barangay"
    },
    "name": {
      "local": "Samporna (Pob.)",
      "en": "Samporna (Pob.)",
      "slug": "samporna-pob-153604041"
    },
    "code": {
      "id": "153604041",
      "iso": null
    },
    "parent": {
      "id": "153604",
      "level": 3,
      "name": {
        "local": "Bayang",
        "en": "Bayang",
        "slug": "bayang-153604"
      }
    },
    "ancestors": [
      {
        "id": "ARMM",
        "level": 1,
        "name": {
          "local": "Autonomous Region in Muslim Mindanao",
          "en": "Autonomous Region in Muslim Mindanao",
          "slug": "autonomous-region-in-muslim-mindanao-ARMM"
        }
      },
      {
        "id": "153600",
        "level": 2,
        "name": {
          "local": "Lanao del Sur",
          "en": "Lanao del Sur",
          "slug": "lanao-del-sur-153600"
        }
      },
      {
        "id": "153604",
        "level": 3,
        "name": {
          "local": "Bayang",
          "en": "Bayang",
          "slug": "bayang-153604"
        }
      }
    ],
    "children_count": {},
    "zip_codes": [
      "9309"
    ],
    "geo": {
      "lat": "7.79306",
      "lon": "124.19194"
    },
    "metadata": {},
    "source": {}
  },
  {
    "id": "153604040",
    "level": 4,
    "level_name": {
      "local": "Barangay",
      "en": "Barangay"
    },
    "name": {
      "local": "Sapa",
      "en": "Sapa",
      "slug": "sapa-153604040"
    },
    "code": {
      "id": "153604040",
      "iso": null
    },
    "parent": {
      "id": "153604",
      "level": 3,
      "name": {
        "local": "Bayang",
        "en": "Bayang",
        "slug": "bayang-153604"
      }
    },
    "ancestors": [
      {
        "id": "ARMM",
        "level": 1,
        "name": {
          "local": "Autonomous Region in Muslim Mindanao",
          "en": "Autonomous Region in Muslim Mindanao",
          "slug": "autonomous-region-in-muslim-mindanao-ARMM"
        }
      },
      {
        "id": "153600",
        "level": 2,
        "name": {
          "local": "Lanao del Sur",
          "en": "Lanao del Sur",
          "slug": "lanao-del-sur-153600"
        }
      },
      {
        "id": "153604",
        "level": 3,
        "name": {
          "local": "Bayang",
          "en": "Bayang",
          "slug": "bayang-153604"
        }
      }
    ],
    "children_count": {},
    "zip_codes": [
      "9309"
    ],
    "geo": {
      "lat": "7.7968",
      "lon": "124.1764"
    },
    "metadata": {},
    "source": {}
  },
  {
    "id": "153604042",
    "level": 4,
    "level_name": {
      "local": "Barangay",
      "en": "Barangay"
    },
    "name": {
      "local": "Silid",
      "en": "Silid",
      "slug": "silid-153604042"
    },
    "code": {
      "id": "153604042",
      "iso": null
    },
    "parent": {
      "id": "153604",
      "level": 3,
      "name": {
        "local": "Bayang",
        "en": "Bayang",
        "slug": "bayang-153604"
      }
    },
    "ancestors": [
      {
        "id": "ARMM",
        "level": 1,
        "name": {
          "local": "Autonomous Region in Muslim Mindanao",
          "en": "Autonomous Region in Muslim Mindanao",
          "slug": "autonomous-region-in-muslim-mindanao-ARMM"
        }
      },
      {
        "id": "153600",
        "level": 2,
        "name": {
          "local": "Lanao del Sur",
          "en": "Lanao del Sur",
          "slug": "lanao-del-sur-153600"
        }
      },
      {
        "id": "153604",
        "level": 3,
        "name": {
          "local": "Bayang",
          "en": "Bayang",
          "slug": "bayang-153604"
        }
      }
    ],
    "children_count": {},
    "zip_codes": [
      "9309"
    ],
    "geo": {
      "lat": "7.79306",
      "lon": "124.19194"
    },
    "metadata": {},
    "source": {}
  },
  {
    "id": "153604043",
    "level": 4,
    "level_name": {
      "local": "Barangay",
      "en": "Barangay"
    },
    "name": {
      "local": "Sugod",
      "en": "Sugod",
      "slug": "sugod-153604043"
    },
    "code": {
      "id": "153604043",
      "iso": null
    },
    "parent": {
      "id": "153604",
      "level": 3,
      "name": {
        "local": "Bayang",
        "en": "Bayang",
        "slug": "bayang-153604"
      }
    },
    "ancestors": [
      {
        "id": "ARMM",
        "level": 1,
        "name": {
          "local": "Autonomous Region in Muslim Mindanao",
          "en": "Autonomous Region in Muslim Mindanao",
          "slug": "autonomous-region-in-muslim-mindanao-ARMM"
        }
      },
      {
        "id": "153600",
        "level": 2,
        "name": {
          "local": "Lanao del Sur",
          "en": "Lanao del Sur",
          "slug": "lanao-del-sur-153600"
        }
      },
      {
        "id": "153604",
        "level": 3,
        "name": {
          "local": "Bayang",
          "en": "Bayang",
          "slug": "bayang-153604"
        }
      }
    ],
    "children_count": {},
    "zip_codes": [
      "9309"
    ],
    "geo": {
      "lat": "7.85",
      "lon": "124.15"
    },
    "metadata": {},
    "source": {}
  },
  {
    "id": "153604044",
    "level": 4,
    "level_name": {
      "local": "Barangay",
      "en": "Barangay"
    },
    "name": {
      "local": "Sultan Pandapatan",
      "en": "Sultan Pandapatan",
      "slug": "sultan-pandapatan-153604044"
    },
    "code": {
      "id": "153604044",
      "iso": null
    },
    "parent": {
      "id": "153604",
      "level": 3,
      "name": {
        "local": "Bayang",
        "en": "Bayang",
        "slug": "bayang-153604"
      }
    },
    "ancestors": [
      {
        "id": "ARMM",
        "level": 1,
        "name": {
          "local": "Autonomous Region in Muslim Mindanao",
          "en": "Autonomous Region in Muslim Mindanao",
          "slug": "autonomous-region-in-muslim-mindanao-ARMM"
        }
      },
      {
        "id": "153600",
        "level": 2,
        "name": {
          "local": "Lanao del Sur",
          "en": "Lanao del Sur",
          "slug": "lanao-del-sur-153600"
        }
      },
      {
        "id": "153604",
        "level": 3,
        "name": {
          "local": "Bayang",
          "en": "Bayang",
          "slug": "bayang-153604"
        }
      }
    ],
    "children_count": {},
    "zip_codes": [
      "9309"
    ],
    "geo": {
      "lat": "7.79306",
      "lon": "124.19194"
    },
    "metadata": {},
    "source": {}
  },
  {
    "id": "153604045",
    "level": 4,
    "level_name": {
      "local": "Barangay",
      "en": "Barangay"
    },
    "name": {
      "local": "Sumbag (Pob.)",
      "en": "Sumbag (Pob.)",
      "slug": "sumbag-pob-153604045"
    },
    "code": {
      "id": "153604045",
      "iso": null
    },
    "parent": {
      "id": "153604",
      "level": 3,
      "name": {
        "local": "Bayang",
        "en": "Bayang",
        "slug": "bayang-153604"
      }
    },
    "ancestors": [
      {
        "id": "ARMM",
        "level": 1,
        "name": {
          "local": "Autonomous Region in Muslim Mindanao",
          "en": "Autonomous Region in Muslim Mindanao",
          "slug": "autonomous-region-in-muslim-mindanao-ARMM"
        }
      },
      {
        "id": "153600",
        "level": 2,
        "name": {
          "local": "Lanao del Sur",
          "en": "Lanao del Sur",
          "slug": "lanao-del-sur-153600"
        }
      },
      {
        "id": "153604",
        "level": 3,
        "name": {
          "local": "Bayang",
          "en": "Bayang",
          "slug": "bayang-153604"
        }
      }
    ],
    "children_count": {},
    "zip_codes": [
      "9309"
    ],
    "geo": {
      "lat": "7.79306",
      "lon": "124.19194"
    },
    "metadata": {},
    "source": {}
  },
  {
    "id": "153604046",
    "level": 4,
    "level_name": {
      "local": "Barangay",
      "en": "Barangay"
    },
    "name": {
      "local": "Tagoranao",
      "en": "Tagoranao",
      "slug": "tagoranao-153604046"
    },
    "code": {
      "id": "153604046",
      "iso": null
    },
    "parent": {
      "id": "153604",
      "level": 3,
      "name": {
        "local": "Bayang",
        "en": "Bayang",
        "slug": "bayang-153604"
      }
    },
    "ancestors": [
      {
        "id": "ARMM",
        "level": 1,
        "name": {
          "local": "Autonomous Region in Muslim Mindanao",
          "en": "Autonomous Region in Muslim Mindanao",
          "slug": "autonomous-region-in-muslim-mindanao-ARMM"
        }
      },
      {
        "id": "153600",
        "level": 2,
        "name": {
          "local": "Lanao del Sur",
          "en": "Lanao del Sur",
          "slug": "lanao-del-sur-153600"
        }
      },
      {
        "id": "153604",
        "level": 3,
        "name": {
          "local": "Bayang",
          "en": "Bayang",
          "slug": "bayang-153604"
        }
      }
    ],
    "children_count": {},
    "zip_codes": [
      "9309"
    ],
    "geo": {
      "lat": "7.79306",
      "lon": "124.19194"
    },
    "metadata": {},
    "source": {}
  },
  {
    "id": "153604047",
    "level": 4,
    "level_name": {
      "local": "Barangay",
      "en": "Barangay"
    },
    "name": {
      "local": "Tangcal",
      "en": "Tangcal",
      "slug": "tangcal-153604047"
    },
    "code": {
      "id": "153604047",
      "iso": null
    },
    "parent": {
      "id": "153604",
      "level": 3,
      "name": {
        "local": "Bayang",
        "en": "Bayang",
        "slug": "bayang-153604"
      }
    },
    "ancestors": [
      {
        "id": "ARMM",
        "level": 1,
        "name": {
          "local": "Autonomous Region in Muslim Mindanao",
          "en": "Autonomous Region in Muslim Mindanao",
          "slug": "autonomous-region-in-muslim-mindanao-ARMM"
        }
      },
      {
        "id": "153600",
        "level": 2,
        "name": {
          "local": "Lanao del Sur",
          "en": "Lanao del Sur",
          "slug": "lanao-del-sur-153600"
        }
      },
      {
        "id": "153604",
        "level": 3,
        "name": {
          "local": "Bayang",
          "en": "Bayang",
          "slug": "bayang-153604"
        }
      }
    ],
    "children_count": {},
    "zip_codes": [
      "9309"
    ],
    "geo": {
      "lat": "7.74",
      "lon": "124.2117"
    },
    "metadata": {},
    "source": {}
  },
  {
    "id": "153604048",
    "level": 4,
    "level_name": {
      "local": "Barangay",
      "en": "Barangay"
    },
    "name": {
      "local": "Tangcal Proper (Pob.)",
      "en": "Tangcal Proper (Pob.)",
      "slug": "tangcal-proper-pob-153604048"
    },
    "code": {
      "id": "153604048",
      "iso": null
    },
    "parent": {
      "id": "153604",
      "level": 3,
      "name": {
        "local": "Bayang",
        "en": "Bayang",
        "slug": "bayang-153604"
      }
    },
    "ancestors": [
      {
        "id": "ARMM",
        "level": 1,
        "name": {
          "local": "Autonomous Region in Muslim Mindanao",
          "en": "Autonomous Region in Muslim Mindanao",
          "slug": "autonomous-region-in-muslim-mindanao-ARMM"
        }
      },
      {
        "id": "153600",
        "level": 2,
        "name": {
          "local": "Lanao del Sur",
          "en": "Lanao del Sur",
          "slug": "lanao-del-sur-153600"
        }
      },
      {
        "id": "153604",
        "level": 3,
        "name": {
          "local": "Bayang",
          "en": "Bayang",
          "slug": "bayang-153604"
        }
      }
    ],
    "children_count": {},
    "zip_codes": [
      "9309"
    ],
    "geo": {
      "lat": "7.74",
      "lon": "124.2117"
    },
    "metadata": {},
    "source": {}
  },
  {
    "id": "153604050",
    "level": 4,
    "level_name": {
      "local": "Barangay",
      "en": "Barangay"
    },
    "name": {
      "local": "Tomarompong",
      "en": "Tomarompong",
      "slug": "tomarompong-153604050"
    },
    "code": {
      "id": "153604050",
      "iso": null
    },
    "parent": {
      "id": "153604",
      "level": 3,
      "name": {
        "local": "Bayang",
        "en": "Bayang",
        "slug": "bayang-153604"
      }
    },
    "ancestors": [
      {
        "id": "ARMM",
        "level": 1,
        "name": {
          "local": "Autonomous Region in Muslim Mindanao",
          "en": "Autonomous Region in Muslim Mindanao",
          "slug": "autonomous-region-in-muslim-mindanao-ARMM"
        }
      },
      {
        "id": "153600",
        "level": 2,
        "name": {
          "local": "Lanao del Sur",
          "en": "Lanao del Sur",
          "slug": "lanao-del-sur-153600"
        }
      },
      {
        "id": "153604",
        "level": 3,
        "name": {
          "local": "Bayang",
          "en": "Bayang",
          "slug": "bayang-153604"
        }
      }
    ],
    "children_count": {},
    "zip_codes": [
      "9309"
    ],
    "geo": {
      "lat": "7.79306",
      "lon": "124.19194"
    },
    "metadata": {},
    "source": {}
  },
  {
    "id": "153604051",
    "level": 4,
    "level_name": {
      "local": "Barangay",
      "en": "Barangay"
    },
    "name": {
      "local": "Tomongcal Ligi",
      "en": "Tomongcal Ligi",
      "slug": "tomongcal-ligi-153604051"
    },
    "code": {
      "id": "153604051",
      "iso": null
    },
    "parent": {
      "id": "153604",
      "level": 3,
      "name": {
        "local": "Bayang",
        "en": "Bayang",
        "slug": "bayang-153604"
      }
    },
    "ancestors": [
      {
        "id": "ARMM",
        "level": 1,
        "name": {
          "local": "Autonomous Region in Muslim Mindanao",
          "en": "Autonomous Region in Muslim Mindanao",
          "slug": "autonomous-region-in-muslim-mindanao-ARMM"
        }
      },
      {
        "id": "153600",
        "level": 2,
        "name": {
          "local": "Lanao del Sur",
          "en": "Lanao del Sur",
          "slug": "lanao-del-sur-153600"
        }
      },
      {
        "id": "153604",
        "level": 3,
        "name": {
          "local": "Bayang",
          "en": "Bayang",
          "slug": "bayang-153604"
        }
      }
    ],
    "children_count": {},
    "zip_codes": [
      "9309"
    ],
    "geo": {
      "lat": "7.79306",
      "lon": "124.19194"
    },
    "metadata": {},
    "source": {}
  },
  {
    "id": "153604052",
    "level": 4,
    "level_name": {
      "local": "Barangay",
      "en": "Barangay"
    },
    "name": {
      "local": "Torogan",
      "en": "Torogan",
      "slug": "torogan-153604052"
    },
    "code": {
      "id": "153604052",
      "iso": null
    },
    "parent": {
      "id": "153604",
      "level": 3,
      "name": {
        "local": "Bayang",
        "en": "Bayang",
        "slug": "bayang-153604"
      }
    },
    "ancestors": [
      {
        "id": "ARMM",
        "level": 1,
        "name": {
          "local": "Autonomous Region in Muslim Mindanao",
          "en": "Autonomous Region in Muslim Mindanao",
          "slug": "autonomous-region-in-muslim-mindanao-ARMM"
        }
      },
      {
        "id": "153600",
        "level": 2,
        "name": {
          "local": "Lanao del Sur",
          "en": "Lanao del Sur",
          "slug": "lanao-del-sur-153600"
        }
      },
      {
        "id": "153604",
        "level": 3,
        "name": {
          "local": "Bayang",
          "en": "Bayang",
          "slug": "bayang-153604"
        }
      }
    ],
    "children_count": {},
    "zip_codes": [
      "9309"
    ],
    "geo": {
      "lat": "7.79306",
      "lon": "124.19194"
    },
    "metadata": {},
    "source": {}
  },
  {
    "id": "153604049",
    "level": 4,
    "level_name": {
      "local": "Barangay",
      "en": "Barangay"
    },
    "name": {
      "local": "Tuca (Pob.)",
      "en": "Tuca (Pob.)",
      "slug": "tuca-pob-153604049"
    },
    "code": {
      "id": "153604049",
      "iso": null
    },
    "parent": {
      "id": "153604",
      "level": 3,
      "name": {
        "local": "Bayang",
        "en": "Bayang",
        "slug": "bayang-153604"
      }
    },
    "ancestors": [
      {
        "id": "ARMM",
        "level": 1,
        "name": {
          "local": "Autonomous Region in Muslim Mindanao",
          "en": "Autonomous Region in Muslim Mindanao",
          "slug": "autonomous-region-in-muslim-mindanao-ARMM"
        }
      },
      {
        "id": "153600",
        "level": 2,
        "name": {
          "local": "Lanao del Sur",
          "en": "Lanao del Sur",
          "slug": "lanao-del-sur-153600"
        }
      },
      {
        "id": "153604",
        "level": 3,
        "name": {
          "local": "Bayang",
          "en": "Bayang",
          "slug": "bayang-153604"
        }
      }
    ],
    "children_count": {},
    "zip_codes": [
      "9309"
    ],
    "geo": {
      "lat": "7.6623",
      "lon": "123.9771"
    },
    "metadata": {},
    "source": {}
  }
]