[
  {
    "id": "045631001",
    "level": 4,
    "level_name": {
      "local": "Barangay",
      "en": "Barangay"
    },
    "name": {
      "local": "Balungay",
      "en": "Balungay",
      "slug": "balungay-045631001"
    },
    "code": {
      "id": "045631001",
      "iso": null
    },
    "parent": {
      "id": "045631",
      "level": 3,
      "name": {
        "local": "Panukulan",
        "en": "Panukulan",
        "slug": "panukulan-045631"
      }
    },
    "ancestors": [
      {
        "id": "R04A",
        "level": 1,
        "name": {
          "local": "CALABARZON",
          "en": "CALABARZON",
          "slug": "calabarzon-R04A"
        }
      },
      {
        "id": "045600",
        "level": 2,
        "name": {
          "local": "Quezon",
          "en": "Quezon",
          "slug": "quezon-045600"
        }
      },
      {
        "id": "045631",
        "level": 3,
        "name": {
          "local": "Panukulan",
          "en": "Panukulan",
          "slug": "panukulan-045631"
        }
      }
    ],
    "children_count": {},
    "zip_codes": [
      "4339"
    ],
    "geo": {
      "lat": "14.0897",
      "lon": "122.0446"
    },
    "metadata": {},
    "source": {}
  },
  {
    "id": "045631002",
    "level": 4,
    "level_name": {
      "local": "Barangay",
      "en": "Barangay"
    },
    "name": {
      "local": "Bato",
      "en": "Bato",
      "slug": "bato-045631002"
    },
    "code": {
      "id": "045631002",
      "iso": null
    },
    "parent": {
      "id": "045631",
      "level": 3,
      "name": {
        "local": "Panukulan",
        "en": "Panukulan",
        "slug": "panukulan-045631"
      }
    },
    "ancestors": [
      {
        "id": "R04A",
        "level": 1,
        "name": {
          "local": "CALABARZON",
          "en": "CALABARZON",
          "slug": "calabarzon-R04A"
        }
      },
      {
        "id": "045600",
        "level": 2,
        "name": {
          "local": "Quezon",
          "en": "Quezon",
          "slug": "quezon-045600"
        }
      },
      {
        "id": "045631",
        "level": 3,
        "name": {
          "local": "Panukulan",
          "en": "Panukulan",
          "slug": "panukulan-045631"
        }
      }
    ],
    "children_count": {},
    "zip_codes": [
      "4339"
    ],
    "geo": {
      "lat": "13.3578",
      "lon": "123.3678"
    },
    "metadata": {},
    "source": {}
  },
  {
    "id": "045631003",
    "level": 4,
    "level_name": {
      "local": "Barangay",
      "en": "Barangay"
    },
    "name": {
      "local": "Bonbon",
      "en": "Bonbon",
      "slug": "bonbon-045631003"
    },
    "code": {
      "id": "045631003",
      "iso": null
    },
    "parent": {
      "id": "045631",
      "level": 3,
      "name": {
        "local": "Panukulan",
        "en": "Panukulan",
        "slug": "panukulan-045631"
      }
    },
    "ancestors": [
      {
        "id": "R04A",
        "level": 1,
        "name": {
          "local": "CALABARZON",
          "en": "CALABARZON",
          "slug": "calabarzon-R04A"
        }
      },
      {
        "id": "045600",
        "level": 2,
        "name": {
          "local": "Quezon",
          "en": "Quezon",
          "slug": "quezon-045600"
        }
      },
      {
        "id": "045631",
        "level": 3,
        "name": {
          "local": "Panukulan",
          "en": "Panukulan",
          "slug": "panukulan-045631"
        }
      }
    ],
    "children_count": {},
    "zip_codes": [
      "4339"
    ],
    "geo": {
      "lat": "13.4172",
      "lon": "121.1857"
    },
    "metadata": {},
    "source": {}
  },
  {
    "id": "045631004",
    "level": 4,
    "level_name": {
      "local": "Barangay",
      "en": "Barangay"
    },
    "name": {
      "local": "Calasumanga",
      "en": "Calasumanga",
      "slug": "calasumanga-045631004"
    },
    "code": {
      "id": "045631004",
      "iso": null
    },
    "parent": {
      "id": "045631",
      "level": 3,
      "name": {
        "local": "Panukulan",
        "en": "Panukulan",
        "slug": "panukulan-045631"
      }
    },
    "ancestors": [
      {
        "id": "R04A",
        "level": 1,
        "name": {
          "local": "CALABARZON",
          "en": "CALABARZON",
          "slug": "calabarzon-R04A"
        }
      },
      {
        "id": "045600",
        "level": 2,
        "name": {
          "local": "Quezon",
          "en": "Quezon",
          "slug": "quezon-045600"
        }
      },
      {
        "id": "045631",
        "level": 3,
        "name": {
          "local": "Panukulan",
          "en": "Panukulan",
          "slug": "panukulan-045631"
        }
      }
    ],
    "children_count": {},
    "zip_codes": [
      "4339"
    ],
    "geo": {
      "lat": "14.9224",
      "lon": "121.8534"
    },
    "metadata": {},
    "source": {}
  },
  {
    "id": "045631005",
    "level": 4,
    "level_name": {
      "local": "Barangay",
      "en": "Barangay"
    },
    "name": {
      "local": "Kinalagti",
      "en": "Kinalagti",
      "slug": "kinalagti-045631005"
    },
    "code": {
      "id": "045631005",
      "iso": null
    },
    "parent": {
      "id": "045631",
      "level": 3,
      "name": {
        "local": "Panukulan",
        "en": "Panukulan",
        "slug": "panukulan-045631"
      }
    },
    "ancestors": [
      {
        "id": "R04A",
        "level": 1,
        "name": {
          "local": "CALABARZON",
          "en": "CALABARZON",
          "slug": "calabarzon-R04A"
        }
      },
      {
        "id": "045600",
        "level": 2,
        "name": {
          "local": "Quezon",
          "en": "Quezon",
          "slug": "quezon-045600"
        }
      },
      {
        "id": "045631",
        "level": 3,
        "name": {
          "local": "Panukulan",
          "en": "Panukulan",
          "slug": "panukulan-045631"
        }
      }
    ],
    "children_count": {},
    "zip_codes": [
      "4339"
    ],
    "geo": {
      "lat": "14.933",
      "lon": "121.817"
    },
    "metadata": {},
    "source": {}
  },
  {
    "id": "045631006",
    "level": 4,
    "level_name": {
      "local": "Barangay",
      "en": "Barangay"
    },
    "name": {
      "local": "Libo",
      "en": "Libo",
      "slug": "libo-045631006"
    },
    "code": {
      "id": "045631006",
      "iso": null
    },
    "parent": {
      "id": "045631",
      "level": 3,
      "name": {
        "local": "Panukulan",
        "en": "Panukulan",
        "slug": "panukulan-045631"
      }
    },
    "ancestors": [
      {
        "id": "R04A",
        "level": 1,
        "name": {
          "local": "CALABARZON",
          "en": "CALABARZON",
          "slug": "calabarzon-R04A"
        }
      },
      {
        "id": "045600",
        "level": 2,
        "name": {
          "local": "Quezon",
          "en": "Quezon",
          "slug": "quezon-045600"
        }
      },
      {
        "id": "045631",
        "level": 3,
        "name": {
          "local": "Panukulan",
          "en": "Panukulan",
          "slug": "panukulan-045631"
        }
      }
    ],
    "children_count": {},
    "zip_codes": [
      "4339"
    ],
    "geo": {
      "lat": "11.3",
      "lon": "124.6833"
    },
    "metadata": {},
    "source": {}
  },
  {
    "id": "045631007",
    "level": 4,
    "level_name": {
      "local": "Barangay",
      "en": "Barangay"
    },
    "name": {
      "local": "Lipata",
      "en": "Lipata",
      "slug": "lipata-045631007"
    },
    "code": {
      "id": "045631007",
      "iso": null
    },
    "parent": {
      "id": "045631",
      "level": 3,
      "name": {
        "local": "Panukulan",
        "en": "Panukulan",
        "slug": "panukulan-045631"
      }
    },
    "ancestors": [
      {
        "id": "R04A",
        "level": 1,
        "name": {
          "local": "CALABARZON",
          "en": "CALABARZON",
          "slug": "calabarzon-R04A"
        }
      },
      {
        "id": "045600",
        "level": 2,
        "name": {
          "local": "Quezon",
          "en": "Quezon",
          "slug": "quezon-045600"
        }
      },
      {
        "id": "045631",
        "level": 3,
        "name": {
          "local": "Panukulan",
          "en": "Panukulan",
          "slug": "panukulan-045631"
        }
      }
    ],
    "children_count": {},
    "zip_codes": [
      "4339"
    ],
    "geo": {
      "lat": "11.12",
      "lon": "125.22"
    },
    "metadata": {},
    "source": {}
  },
  {
    "id": "045631008",
    "level": 4,
    "level_name": {
      "local": "Barangay",
      "en": "Barangay"
    },
    "name": {
      "local": "Matangkap",
      "en": "Matangkap",
      "slug": "matangkap-045631008"
    },
    "code": {
      "id": "045631008",
      "iso": null
    },
    "parent": {
      "id": "045631",
      "level": 3,
      "name": {
        "local": "Panukulan",
        "en": "Panukulan",
        "slug": "panukulan-045631"
      }
    },
    "ancestors": [
      {
        "id": "R04A",
        "level": 1,
        "name": {
          "local": "CALABARZON",
          "en": "CALABARZON",
          "slug": "calabarzon-R04A"
        }
      },
      {
        "id": "045600",
        "level": 2,
        "name": {
          "local": "Quezon",
          "en": "Quezon",
          "slug": "quezon-045600"
        }
      },
      {
        "id": "045631",
        "level": 3,
        "name": {
          "local": "Panukulan",
          "en": "Panukulan",
          "slug": "panukulan-045631"
        }
      }
    ],
    "children_count": {},
    "zip_codes": [
      "4339"
    ],
    "geo": {
      "lat": "15.0312",
      "lon": "121.8921"
    },
    "metadata": {},
    "source": {}
  },
  {
    "id": "045631009",
    "level": 4,
    "level_name": {
      "local": "Barangay",
      "en": "Barangay"
    },
    "name": {
      "local": "Milawid",
      "en": "Milawid",
      "slug": "milawid-045631009"
    },
    "code": {
      "id": "045631009",
      "iso": null
    },
    "parent": {
      "id": "045631",
      "level": 3,
      "name": {
        "local": "Panukulan",
        "en": "Panukulan",
        "slug": "panukulan-045631"
      }
    },
    "ancestors": [
      {
        "id": "R04A",
        "level": 1,
        "name": {
          "local": "CALABARZON",
          "en": "CALABARZON",
          "slug": "calabarzon-R04A"
        }
      },
      {
        "id": "045600",
        "level": 2,
        "name": {
          "local": "Quezon",
          "en": "Quezon",
          "slug": "quezon-045600"
        }
      },
      {
        "id": "045631",
        "level": 3,
        "name": {
          "local": "Panukulan",
          "en": "Panukulan",
          "slug": "panukulan-045631"
        }
      }
    ],
    "children_count": {},
    "zip_codes": [
      "4339"
    ],
    "geo": {
      "lat": "14.9262",
      "lon": "121.85"
    },
    "metadata": {},
    "source": {}
  },
  {
    "id": "045631010",
    "level": 4,
    "level_name": {
      "local": "Barangay",
      "en": "Barangay"
    },
    "name": {
      "local": "Pagitan",
      "en": "Pagitan",
      "slug": "pagitan-045631010"
    },
    "code": {
      "id": "045631010",
      "iso": null
    },
    "parent": {
      "id": "045631",
      "level": 3,
      "name": {
        "local": "Panukulan",
        "en": "Panukulan",
        "slug": "panukulan-045631"
      }
    },
    "ancestors": [
      {
        "id": "R04A",
        "level": 1,
        "name": {
          "local": "CALABARZON",
          "en": "CALABARZON",
          "slug": "calabarzon-R04A"
        }
      },
      {
        "id": "045600",
        "level": 2,
        "name": {
          "local": "Quezon",
          "en": "Quezon",
          "slug": "quezon-045600"
        }
      },
      {
        "id": "045631",
        "level": 3,
        "name": {
          "local": "Panukulan",
          "en": "Panukulan",
          "slug": "panukulan-045631"
        }
      }
    ],
    "children_count": {},
    "zip_codes": [
      "4339"
    ],
    "geo": {
      "lat": "14.933",
      "lon": "121.817"
    },
    "metadata": {},
    "source": {}
  },
  {
    "id": "045631011",
    "level": 4,
    "level_name": {
      "local": "Barangay",
      "en": "Barangay"
    },
    "name": {
      "local": "Pandan",
      "en": "Pandan",
      "slug": "pandan-045631011"
    },
    "code": {
      "id": "045631011",
      "iso": null
    },
    "parent": {
      "id": "045631",
      "level": 3,
      "name": {
        "local": "Panukulan",
        "en": "Panukulan",
        "slug": "panukulan-045631"
      }
    },
    "ancestors": [
      {
        "id": "R04A",
        "level": 1,
        "name": {
          "local": "CALABARZON",
          "en": "CALABARZON",
          "slug": "calabarzon-R04A"
        }
      },
      {
        "id": "045600",
        "level": 2,
        "name": {
          "local": "Quezon",
          "en": "Quezon",
          "slug": "quezon-045600"
        }
      },
      {
        "id": "045631",
        "level": 3,
        "name": {
          "local": "Panukulan",
          "en": "Panukulan",
          "slug": "panukulan-045631"
        }
      }
    ],
    "children_count": {},
    "zip_codes": [
      "4339"
    ],
    "geo": {
      "lat": "11.7206",
      "lon": "122.0961"
    },
    "metadata": {},
    "source": {}
  },
  {
    "id": "045631012",
    "level": 4,
    "level_name": {
      "local": "Barangay",
      "en": "Barangay"
    },
    "name": {
      "local": "San Juan (Pob.)",
      "en": "San Juan (Pob.)",
      "slug": "san-juan-pob-045631012"
    },
    "code": {
      "id": "045631012",
      "iso": null
    },
    "parent": {
      "id": "045631",
      "level": 3,
      "name": {
        "local": "Panukulan",
        "en": "Panukulan",
        "slug": "panukulan-045631"
      }
    },
    "ancestors": [
      {
        "id": "R04A",
        "level": 1,
        "name": {
          "local": "CALABARZON",
          "en": "CALABARZON",
          "slug": "calabarzon-R04A"
        }
      },
      {
        "id": "045600",
        "level": 2,
        "name": {
          "local": "Quezon",
          "en": "Quezon",
          "slug": "quezon-045600"
        }
      },
      {
        "id": "045631",
        "level": 3,
        "name": {
          "local": "Panukulan",
          "en": "Panukulan",
          "slug": "panukulan-045631"
        }
      }
    ],
    "children_count": {},
    "zip_codes": [
      "4339"
    ],
    "geo": {
      "lat": "14.604",
      "lon": "121.03"
    },
    "metadata": {},
    "source": {}
  }
]