[
  {
    "id": "015545001",
    "level": 4,
    "level_name": {
      "local": "Barangay",
      "en": "Barangay"
    },
    "name": {
      "local": "Angatel",
      "en": "Angatel",
      "slug": "angatel-015545001"
    },
    "code": {
      "id": "015545001",
      "iso": null
    },
    "parent": {
      "id": "015545",
      "level": 3,
      "name": {
        "local": "Urbiztondo",
        "en": "Urbiztondo",
        "slug": "urbiztondo-015545"
      }
    },
    "ancestors": [
      {
        "id": "R01",
        "level": 1,
        "name": {
          "local": "Ilocos Region",
          "en": "Ilocos Region",
          "slug": "ilocos-region-R01"
        }
      },
      {
        "id": "015500",
        "level": 2,
        "name": {
          "local": "Pangasinan",
          "en": "Pangasinan",
          "slug": "pangasinan-015500"
        }
      },
      {
        "id": "015545",
        "level": 3,
        "name": {
          "local": "Urbiztondo",
          "en": "Urbiztondo",
          "slug": "urbiztondo-015545"
        }
      }
    ],
    "children_count": {},
    "zip_codes": [
      "2414"
    ],
    "geo": {
      "lat": "15.8059",
      "lon": "120.3433"
    },
    "metadata": {},
    "source": {}
  },
  {
    "id": "015545002",
    "level": 4,
    "level_name": {
      "local": "Barangay",
      "en": "Barangay"
    },
    "name": {
      "local": "Balangay",
      "en": "Balangay",
      "slug": "balangay-015545002"
    },
    "code": {
      "id": "015545002",
      "iso": null
    },
    "parent": {
      "id": "015545",
      "level": 3,
      "name": {
        "local": "Urbiztondo",
        "en": "Urbiztondo",
        "slug": "urbiztondo-015545"
      }
    },
    "ancestors": [
      {
        "id": "R01",
        "level": 1,
        "name": {
          "local": "Ilocos Region",
          "en": "Ilocos Region",
          "slug": "ilocos-region-R01"
        }
      },
      {
        "id": "015500",
        "level": 2,
        "name": {
          "local": "Pangasinan",
          "en": "Pangasinan",
          "slug": "pangasinan-015500"
        }
      },
      {
        "id": "015545",
        "level": 3,
        "name": {
          "local": "Urbiztondo",
          "en": "Urbiztondo",
          "slug": "urbiztondo-015545"
        }
      }
    ],
    "children_count": {},
    "zip_codes": [
      "2414"
    ],
    "geo": {
      "lat": "15.8548",
      "lon": "120.363"
    },
    "metadata": {},
    "source": {}
  },
  {
    "id": "015545003",
    "level": 4,
    "level_name": {
      "local": "Barangay",
      "en": "Barangay"
    },
    "name": {
      "local": "Batangcaoa",
      "en": "Batangcaoa",
      "slug": "batangcaoa-015545003"
    },
    "code": {
      "id": "015545003",
      "iso": null
    },
    "parent": {
      "id": "015545",
      "level": 3,
      "name": {
        "local": "Urbiztondo",
        "en": "Urbiztondo",
        "slug": "urbiztondo-015545"
      }
    },
    "ancestors": [
      {
        "id": "R01",
        "level": 1,
        "name": {
          "local": "Ilocos Region",
          "en": "Ilocos Region",
          "slug": "ilocos-region-R01"
        }
      },
      {
        "id": "015500",
        "level": 2,
        "name": {
          "local": "Pangasinan",
          "en": "Pangasinan",
          "slug": "pangasinan-015500"
        }
      },
      {
        "id": "015545",
        "level": 3,
        "name": {
          "local": "Urbiztondo",
          "en": "Urbiztondo",
          "slug": "urbiztondo-015545"
        }
      }
    ],
    "children_count": {},
    "zip_codes": [
      "2414"
    ],
    "geo": {
      "lat": "15.8325",
      "lon": "120.3761"
    },
    "metadata": {},
    "source": {}
  },
  {
    "id": "015545004",
    "level": 4,
    "level_name": {
      "local": "Barangay",
      "en": "Barangay"
    },
    "name": {
      "local": "Baug",
      "en": "Baug",
      "slug": "baug-015545004"
    },
    "code": {
      "id": "015545004",
      "iso": null
    },
    "parent": {
      "id": "015545",
      "level": 3,
      "name": {
        "local": "Urbiztondo",
        "en": "Urbiztondo",
        "slug": "urbiztondo-015545"
      }
    },
    "ancestors": [
      {
        "id": "R01",
        "level": 1,
        "name": {
          "local": "Ilocos Region",
          "en": "Ilocos Region",
          "slug": "ilocos-region-R01"
        }
      },
      {
        "id": "015500",
        "level": 2,
        "name": {
          "local": "Pangasinan",
          "en": "Pangasinan",
          "slug": "pangasinan-015500"
        }
      },
      {
        "id": "015545",
        "level": 3,
        "name": {
          "local": "Urbiztondo",
          "en": "Urbiztondo",
          "slug": "urbiztondo-015545"
        }
      }
    ],
    "children_count": {},
    "zip_codes": [
      "2414"
    ],
    "geo": {
      "lat": "15.8172",
      "lon": "120.3699"
    },
    "metadata": {},
    "source": {}
  },
  {
    "id": "015545005",
    "level": 4,
    "level_name": {
      "local": "Barangay",
      "en": "Barangay"
    },
    "name": {
      "local": "Bayaoas",
      "en": "Bayaoas",
      "slug": "bayaoas-015545005"
    },
    "code": {
      "id": "015545005",
      "iso": null
    },
    "parent": {
      "id": "015545",
      "level": 3,
      "name": {
        "local": "Urbiztondo",
        "en": "Urbiztondo",
        "slug": "urbiztondo-015545"
      }
    },
    "ancestors": [
      {
        "id": "R01",
        "level": 1,
        "name": {
          "local": "Ilocos Region",
          "en": "Ilocos Region",
          "slug": "ilocos-region-R01"
        }
      },
      {
        "id": "015500",
        "level": 2,
        "name": {
          "local": "Pangasinan",
          "en": "Pangasinan",
          "slug": "pangasinan-015500"
        }
      },
      {
        "id": "015545",
        "level": 3,
        "name": {
          "local": "Urbiztondo",
          "en": "Urbiztondo",
          "slug": "urbiztondo-015545"
        }
      }
    ],
    "children_count": {},
    "zip_codes": [
      "2414"
    ],
    "geo": {
      "lat": "15.9765",
      "lon": "120.5785"
    },
    "metadata": {},
    "source": {}
  },
  {
    "id": "015545006",
    "level": 4,
    "level_name": {
      "local": "Barangay",
      "en": "Barangay"
    },
    "name": {
      "local": "Bituag",
      "en": "Bituag",
      "slug": "bituag-015545006"
    },
    "code": {
      "id": "015545006",
      "iso": null
    },
    "parent": {
      "id": "015545",
      "level": 3,
      "name": {
        "local": "Urbiztondo",
        "en": "Urbiztondo",
        "slug": "urbiztondo-015545"
      }
    },
    "ancestors": [
      {
        "id": "R01",
        "level": 1,
        "name": {
          "local": "Ilocos Region",
          "en": "Ilocos Region",
          "slug": "ilocos-region-R01"
        }
      },
      {
        "id": "015500",
        "level": 2,
        "name": {
          "local": "Pangasinan",
          "en": "Pangasinan",
          "slug": "pangasinan-015500"
        }
      },
      {
        "id": "015545",
        "level": 3,
        "name": {
          "local": "Urbiztondo",
          "en": "Urbiztondo",
          "slug": "urbiztondo-015545"
        }
      }
    ],
    "children_count": {},
    "zip_codes": [
      "2414"
    ],
    "geo": {
      "lat": "15.8415",
      "lon": "120.3828"
    },
    "metadata": {},
    "source": {}
  },
  {
    "id": "015545007",
    "level": 4,
    "level_name": {
      "local": "Barangay",
      "en": "Barangay"
    },
    "name": {
      "local": "Camambugan",
      "en": "Camambugan",
      "slug": "camambugan-015545007"
    },
    "code": {
      "id": "015545007",
      "iso": null
    },
    "parent": {
      "id": "015545",
      "level": 3,
      "name": {
        "local": "Urbiztondo",
        "en": "Urbiztondo",
        "slug": "urbiztondo-015545"
      }
    },
    "ancestors": [
      {
        "id": "R01",
        "level": 1,
        "name": {
          "local": "Ilocos Region",
          "en": "Ilocos Region",
          "slug": "ilocos-region-R01"
        }
      },
      {
        "id": "015500",
        "level": 2,
        "name": {
          "local": "Pangasinan",
          "en": "Pangasinan",
          "slug": "pangasinan-015500"
        }
      },
      {
        "id": "015545",
        "level": 3,
        "name": {
          "local": "Urbiztondo",
          "en": "Urbiztondo",
          "slug": "urbiztondo-015545"
        }
      }
    ],
    "children_count": {},
    "zip_codes": [
      "2414"
    ],
    "geo": {
      "lat": "15.8187",
      "lon": "120.3553"
    },
    "metadata": {},
    "source": {}
  },
  {
    "id": "015545008",
    "level": 4,
    "level_name": {
      "local": "Barangay",
      "en": "Barangay"
    },
    "name": {
      "local": "Dalangiring",
      "en": "Dalangiring",
      "slug": "dalangiring-015545008"
    },
    "code": {
      "id": "015545008",
      "iso": null
    },
    "parent": {
      "id": "015545",
      "level": 3,
      "name": {
        "local": "Urbiztondo",
        "en": "Urbiztondo",
        "slug": "urbiztondo-015545"
      }
    },
    "ancestors": [
      {
        "id": "R01",
        "level": 1,
        "name": {
          "local": "Ilocos Region",
          "en": "Ilocos Region",
          "slug": "ilocos-region-R01"
        }
      },
      {
        "id": "015500",
        "level": 2,
        "name": {
          "local": "Pangasinan",
          "en": "Pangasinan",
          "slug": "pangasinan-015500"
        }
      },
      {
        "id": "015545",
        "level": 3,
        "name": {
          "local": "Urbiztondo",
          "en": "Urbiztondo",
          "slug": "urbiztondo-015545"
        }
      }
    ],
    "children_count": {},
    "zip_codes": [
      "2414"
    ],
    "geo": {
      "lat": "15.8404",
      "lon": "120.3308"
    },
    "metadata": {},
    "source": {}
  },
  {
    "id": "015545009",
    "level": 4,
    "level_name": {
      "local": "Barangay",
      "en": "Barangay"
    },
    "name": {
      "local": "Duplac",
      "en": "Duplac",
      "slug": "duplac-015545009"
    },
    "code": {
      "id": "015545009",
      "iso": null
    },
    "parent": {
      "id": "015545",
      "level": 3,
      "name": {
        "local": "Urbiztondo",
        "en": "Urbiztondo",
        "slug": "urbiztondo-015545"
      }
    },
    "ancestors": [
      {
        "id": "R01",
        "level": 1,
        "name": {
          "local": "Ilocos Region",
          "en": "Ilocos Region",
          "slug": "ilocos-region-R01"
        }
      },
      {
        "id": "015500",
        "level": 2,
        "name": {
          "local": "Pangasinan",
          "en": "Pangasinan",
          "slug": "pangasinan-015500"
        }
      },
      {
        "id": "015545",
        "level": 3,
        "name": {
          "local": "Urbiztondo",
          "en": "Urbiztondo",
          "slug": "urbiztondo-015545"
        }
      }
    ],
    "children_count": {},
    "zip_codes": [
      "2414"
    ],
    "geo": {
      "lat": "15.8495",
      "lon": "120.365"
    },
    "metadata": {},
    "source": {}
  },
  {
    "id": "015545010",
    "level": 4,
    "level_name": {
      "local": "Barangay",
      "en": "Barangay"
    },
    "name": {
      "local": "Galarin",
      "en": "Galarin",
      "slug": "galarin-015545010"
    },
    "code": {
      "id": "015545010",
      "iso": null
    },
    "parent": {
      "id": "015545",
      "level": 3,
      "name": {
        "local": "Urbiztondo",
        "en": "Urbiztondo",
        "slug": "urbiztondo-015545"
      }
    },
    "ancestors": [
      {
        "id": "R01",
        "level": 1,
        "name": {
          "local": "Ilocos Region",
          "en": "Ilocos Region",
          "slug": "ilocos-region-R01"
        }
      },
      {
        "id": "015500",
        "level": 2,
        "name": {
          "local": "Pangasinan",
          "en": "Pangasinan",
          "slug": "pangasinan-015500"
        }
      },
      {
        "id": "015545",
        "level": 3,
        "name": {
          "local": "Urbiztondo",
          "en": "Urbiztondo",
          "slug": "urbiztondo-015545"
        }
      }
    ],
    "children_count": {},
    "zip_codes": [
      "2414"
    ],
    "geo": {
      "lat": "15.7977",
      "lon": "120.365"
    },
    "metadata": {},
    "source": {}
  },
  {
    "id": "015545011",
    "level": 4,
    "level_name": {
      "local": "Barangay",
      "en": "Barangay"
    },
    "name": {
      "local": "Gueteb",
      "en": "Gueteb",
      "slug": "gueteb-015545011"
    },
    "code": {
      "id": "015545011",
      "iso": null
    },
    "parent": {
      "id": "015545",
      "level": 3,
      "name": {
        "local": "Urbiztondo",
        "en": "Urbiztondo",
        "slug": "urbiztondo-015545"
      }
    },
    "ancestors": [
      {
        "id": "R01",
        "level": 1,
        "name": {
          "local": "Ilocos Region",
          "en": "Ilocos Region",
          "slug": "ilocos-region-R01"
        }
      },
      {
        "id": "015500",
        "level": 2,
        "name": {
          "local": "Pangasinan",
          "en": "Pangasinan",
          "slug": "pangasinan-015500"
        }
      },
      {
        "id": "015545",
        "level": 3,
        "name": {
          "local": "Urbiztondo",
          "en": "Urbiztondo",
          "slug": "urbiztondo-015545"
        }
      }
    ],
    "children_count": {},
    "zip_codes": [
      "2414"
    ],
    "geo": {
      "lat": "15.8467",
      "lon": "120.3535"
    },
    "metadata": {},
    "source": {}
  },
  {
    "id": "015545012",
    "level": 4,
    "level_name": {
      "local": "Barangay",
      "en": "Barangay"
    },
    "name": {
      "local": "Malaca",
      "en": "Malaca",
      "slug": "malaca-015545012"
    },
    "code": {
      "id": "015545012",
      "iso": null
    },
    "parent": {
      "id": "015545",
      "level": 3,
      "name": {
        "local": "Urbiztondo",
        "en": "Urbiztondo",
        "slug": "urbiztondo-015545"
      }
    },
    "ancestors": [
      {
        "id": "R01",
        "level": 1,
        "name": {
          "local": "Ilocos Region",
          "en": "Ilocos Region",
          "slug": "ilocos-region-R01"
        }
      },
      {
        "id": "015500",
        "level": 2,
        "name": {
          "local": "Pangasinan",
          "en": "Pangasinan",
          "slug": "pangasinan-015500"
        }
      },
      {
        "id": "015545",
        "level": 3,
        "name": {
          "local": "Urbiztondo",
          "en": "Urbiztondo",
          "slug": "urbiztondo-015545"
        }
      }
    ],
    "children_count": {},
    "zip_codes": [
      "2414"
    ],
    "geo": {
      "lat": "15.8391",
      "lon": "120.3709"
    },
    "metadata": {},
    "source": {}
  },
  {
    "id": "015545013",
    "level": 4,
    "level_name": {
      "local": "Barangay",
      "en": "Barangay"
    },
    "name": {
      "local": "Malayo",
      "en": "Malayo",
      "slug": "malayo-015545013"
    },
    "code": {
      "id": "015545013",
      "iso": null
    },
    "parent": {
      "id": "015545",
      "level": 3,
      "name": {
        "local": "Urbiztondo",
        "en": "Urbiztondo",
        "slug": "urbiztondo-015545"
      }
    },
    "ancestors": [
      {
        "id": "R01",
        "level": 1,
        "name": {
          "local": "Ilocos Region",
          "en": "Ilocos Region",
          "slug": "ilocos-region-R01"
        }
      },
      {
        "id": "015500",
        "level": 2,
        "name": {
          "local": "Pangasinan",
          "en": "Pangasinan",
          "slug": "pangasinan-015500"
        }
      },
      {
        "id": "015545",
        "level": 3,
        "name": {
          "local": "Urbiztondo",
          "en": "Urbiztondo",
          "slug": "urbiztondo-015545"
        }
      }
    ],
    "children_count": {},
    "zip_codes": [
      "2414"
    ],
    "geo": {
      "lat": "15.8238",
      "lon": "120.3441"
    },
    "metadata": {},
    "source": {}
  },
  {
    "id": "015545014",
    "level": 4,
    "level_name": {
      "local": "Barangay",
      "en": "Barangay"
    },
    "name": {
      "local": "Malibong",
      "en": "Malibong",
      "slug": "malibong-015545014"
    },
    "code": {
      "id": "015545014",
      "iso": null
    },
    "parent": {
      "id": "015545",
      "level": 3,
      "name": {
        "local": "Urbiztondo",
        "en": "Urbiztondo",
        "slug": "urbiztondo-015545"
      }
    },
    "ancestors": [
      {
        "id": "R01",
        "level": 1,
        "name": {
          "local": "Ilocos Region",
          "en": "Ilocos Region",
          "slug": "ilocos-region-R01"
        }
      },
      {
        "id": "015500",
        "level": 2,
        "name": {
          "local": "Pangasinan",
          "en": "Pangasinan",
          "slug": "pangasinan-015500"
        }
      },
      {
        "id": "015545",
        "level": 3,
        "name": {
          "local": "Urbiztondo",
          "en": "Urbiztondo",
          "slug": "urbiztondo-015545"
        }
      }
    ],
    "children_count": {},
    "zip_codes": [
      "2414"
    ],
    "geo": {
      "lat": "15.8466",
      "lon": "120.3269"
    },
    "metadata": {},
    "source": {}
  },
  {
    "id": "015545015",
    "level": 4,
    "level_name": {
      "local": "Barangay",
      "en": "Barangay"
    },
    "name": {
      "local": "Pasibi East",
      "en": "Pasibi East",
      "slug": "pasibi-east-015545015"
    },
    "code": {
      "id": "015545015",
      "iso": null
    },
    "parent": {
      "id": "015545",
      "level": 3,
      "name": {
        "local": "Urbiztondo",
        "en": "Urbiztondo",
        "slug": "urbiztondo-015545"
      }
    },
    "ancestors": [
      {
        "id": "R01",
        "level": 1,
        "name": {
          "local": "Ilocos Region",
          "en": "Ilocos Region",
          "slug": "ilocos-region-R01"
        }
      },
      {
        "id": "015500",
        "level": 2,
        "name": {
          "local": "Pangasinan",
          "en": "Pangasinan",
          "slug": "pangasinan-015500"
        }
      },
      {
        "id": "015545",
        "level": 3,
        "name": {
          "local": "Urbiztondo",
          "en": "Urbiztondo",
          "slug": "urbiztondo-015545"
        }
      }
    ],
    "children_count": {},
    "zip_codes": [
      "2414"
    ],
    "geo": {
      "lat": "15.8503",
      "lon": "120.3825"
    },
    "metadata": {},
    "source": {}
  },
  {
    "id": "015545016",
    "level": 4,
    "level_name": {
      "local": "Barangay",
      "en": "Barangay"
    },
    "name": {
      "local": "Pasibi West",
      "en": "Pasibi West",
      "slug": "pasibi-west-015545016"
    },
    "code": {
      "id": "015545016",
      "iso": null
    },
    "parent": {
      "id": "015545",
      "level": 3,
      "name": {
        "local": "Urbiztondo",
        "en": "Urbiztondo",
        "slug": "urbiztondo-015545"
      }
    },
    "ancestors": [
      {
        "id": "R01",
        "level": 1,
        "name": {
          "local": "Ilocos Region",
          "en": "Ilocos Region",
          "slug": "ilocos-region-R01"
        }
      },
      {
        "id": "015500",
        "level": 2,
        "name": {
          "local": "Pangasinan",
          "en": "Pangasinan",
          "slug": "pangasinan-015500"
        }
      },
      {
        "id": "015545",
        "level": 3,
        "name": {
          "local": "Urbiztondo",
          "en": "Urbiztondo",
          "slug": "urbiztondo-015545"
        }
      }
    ],
    "children_count": {},
    "zip_codes": [
      "2414"
    ],
    "geo": {
      "lat": "15.8587",
      "lon": "120.3793"
    },
    "metadata": {},
    "source": {}
  },
  {
    "id": "015545017",
    "level": 4,
    "level_name": {
      "local": "Barangay",
      "en": "Barangay"
    },
    "name": {
      "local": "Pisuac",
      "en": "Pisuac",
      "slug": "pisuac-015545017"
    },
    "code": {
      "id": "015545017",
      "iso": null
    },
    "parent": {
      "id": "015545",
      "level": 3,
      "name": {
        "local": "Urbiztondo",
        "en": "Urbiztondo",
        "slug": "urbiztondo-015545"
      }
    },
    "ancestors": [
      {
        "id": "R01",
        "level": 1,
        "name": {
          "local": "Ilocos Region",
          "en": "Ilocos Region",
          "slug": "ilocos-region-R01"
        }
      },
      {
        "id": "015500",
        "level": 2,
        "name": {
          "local": "Pangasinan",
          "en": "Pangasinan",
          "slug": "pangasinan-015500"
        }
      },
      {
        "id": "015545",
        "level": 3,
        "name": {
          "local": "Urbiztondo",
          "en": "Urbiztondo",
          "slug": "urbiztondo-015545"
        }
      }
    ],
    "children_count": {},
    "zip_codes": [
      "2414"
    ],
    "geo": {
      "lat": "15.8046",
      "lon": "120.3607"
    },
    "metadata": {},
    "source": {}
  },
  {
    "id": "015545018",
    "level": 4,
    "level_name": {
      "local": "Barangay",
      "en": "Barangay"
    },
    "name": {
      "local": "Poblacion",
      "en": "Poblacion",
      "slug": "poblacion-015545018"
    },
    "code": {
      "id": "015545018",
      "iso": null
    },
    "parent": {
      "id": "015545",
      "level": 3,
      "name": {
        "local": "Urbiztondo",
        "en": "Urbiztondo",
        "slug": "urbiztondo-015545"
      }
    },
    "ancestors": [
      {
        "id": "R01",
        "level": 1,
        "name": {
          "local": "Ilocos Region",
          "en": "Ilocos Region",
          "slug": "ilocos-region-R01"
        }
      },
      {
        "id": "015500",
        "level": 2,
        "name": {
          "local": "Pangasinan",
          "en": "Pangasinan",
          "slug": "pangasinan-015500"
        }
      },
      {
        "id": "015545",
        "level": 3,
        "name": {
          "local": "Urbiztondo",
          "en": "Urbiztondo",
          "slug": "urbiztondo-015545"
        }
      }
    ],
    "children_count": {},
    "zip_codes": [
      "2414"
    ],
    "geo": {
      "lat": "15.9747",
      "lon": "120.5637"
    },
    "metadata": {},
    "source": {}
  },
  {
    "id": "015545019",
    "level": 4,
    "level_name": {
      "local": "Barangay",
      "en": "Barangay"
    },
    "name": {
      "local": "Real",
      "en": "Real",
      "slug": "real-015545019"
    },
    "code": {
      "id": "015545019",
      "iso": null
    },
    "parent": {
      "id": "015545",
      "level": 3,
      "name": {
        "local": "Urbiztondo",
        "en": "Urbiztondo",
        "slug": "urbiztondo-015545"
      }
    },
    "ancestors": [
      {
        "id": "R01",
        "level": 1,
        "name": {
          "local": "Ilocos Region",
          "en": "Ilocos Region",
          "slug": "ilocos-region-R01"
        }
      },
      {
        "id": "015500",
        "level": 2,
        "name": {
          "local": "Pangasinan",
          "en": "Pangasinan",
          "slug": "pangasinan-015500"
        }
      },
      {
        "id": "015545",
        "level": 3,
        "name": {
          "local": "Urbiztondo",
          "en": "Urbiztondo",
          "slug": "urbiztondo-015545"
        }
      }
    ],
    "children_count": {},
    "zip_codes": [
      "2414"
    ],
    "geo": {
      "lat": "15.8089",
      "lon": "120.3455"
    },
    "metadata": {},
    "source": {}
  },
  {
    "id": "015545020",
    "level": 4,
    "level_name": {
      "local": "Barangay",
      "en": "Barangay"
    },
    "name": {
      "local": "Salavante",
      "en": "Salavante",
      "slug": "salavante-015545020"
    },
    "code": {
      "id": "015545020",
      "iso": null
    },
    "parent": {
      "id": "015545",
      "level": 3,
      "name": {
        "local": "Urbiztondo",
        "en": "Urbiztondo",
        "slug": "urbiztondo-015545"
      }
    },
    "ancestors": [
      {
        "id": "R01",
        "level": 1,
        "name": {
          "local": "Ilocos Region",
          "en": "Ilocos Region",
          "slug": "ilocos-region-R01"
        }
      },
      {
        "id": "015500",
        "level": 2,
        "name": {
          "local": "Pangasinan",
          "en": "Pangasinan",
          "slug": "pangasinan-015500"
        }
      },
      {
        "id": "015545",
        "level": 3,
        "name": {
          "local": "Urbiztondo",
          "en": "Urbiztondo",
          "slug": "urbiztondo-015545"
        }
      }
    ],
    "children_count": {},
    "zip_codes": [
      "2414"
    ],
    "geo": {
      "lat": "15.7874",
      "lon": "120.3379"
    },
    "metadata": {},
    "source": {}
  },
  {
    "id": "015545021",
    "level": 4,
    "level_name": {
      "local": "Barangay",
      "en": "Barangay"
    },
    "name": {
      "local": "Sawat",
      "en": "Sawat",
      "slug": "sawat-015545021"
    },
    "code": {
      "id": "015545021",
      "iso": null
    },
    "parent": {
      "id": "015545",
      "level": 3,
      "name": {
        "local": "Urbiztondo",
        "en": "Urbiztondo",
        "slug": "urbiztondo-015545"
      }
    },
    "ancestors": [
      {
        "id": "R01",
        "level": 1,
        "name": {
          "local": "Ilocos Region",
          "en": "Ilocos Region",
          "slug": "ilocos-region-R01"
        }
      },
      {
        "id": "015500",
        "level": 2,
        "name": {
          "local": "Pangasinan",
          "en": "Pangasinan",
          "slug": "pangasinan-015500"
        }
      },
      {
        "id": "015545",
        "level": 3,
        "name": {
          "local": "Urbiztondo",
          "en": "Urbiztondo",
          "slug": "urbiztondo-015545"
        }
      }
    ],
    "children_count": {},
    "zip_codes": [
      "2414"
    ],
    "geo": {
      "lat": "15.802",
      "lon": "120.3332"
    },
    "metadata": {},
    "source": {}
  }
]