[
  {
    "id": "101306001",
    "level": 4,
    "level_name": {
      "local": "Barangay",
      "en": "Barangay"
    },
    "name": {
      "local": "Bagongbayan",
      "en": "Bagongbayan",
      "slug": "bagongbayan-101306001"
    },
    "code": {
      "id": "101306001",
      "iso": null
    },
    "parent": {
      "id": "101306",
      "level": 3,
      "name": {
        "local": "Kadingilan",
        "en": "Kadingilan",
        "slug": "kadingilan-101306"
      }
    },
    "ancestors": [
      {
        "id": "R10",
        "level": 1,
        "name": {
          "local": "Northern Mindanao",
          "en": "Northern Mindanao",
          "slug": "northern-mindanao-R10"
        }
      },
      {
        "id": "101300",
        "level": 2,
        "name": {
          "local": "Bukidnon",
          "en": "Bukidnon",
          "slug": "bukidnon-101300"
        }
      },
      {
        "id": "101306",
        "level": 3,
        "name": {
          "local": "Kadingilan",
          "en": "Kadingilan",
          "slug": "kadingilan-101306"
        }
      }
    ],
    "children_count": {},
    "zip_codes": [
      "8713"
    ],
    "geo": {
      "lat": "14.2694",
      "lon": "121.3967"
    },
    "metadata": {},
    "source": {}
  },
  {
    "id": "101306002",
    "level": 4,
    "level_name": {
      "local": "Barangay",
      "en": "Barangay"
    },
    "name": {
      "local": "Bagor",
      "en": "Bagor",
      "slug": "bagor-101306002"
    },
    "code": {
      "id": "101306002",
      "iso": null
    },
    "parent": {
      "id": "101306",
      "level": 3,
      "name": {
        "local": "Kadingilan",
        "en": "Kadingilan",
        "slug": "kadingilan-101306"
      }
    },
    "ancestors": [
      {
        "id": "R10",
        "level": 1,
        "name": {
          "local": "Northern Mindanao",
          "en": "Northern Mindanao",
          "slug": "northern-mindanao-R10"
        }
      },
      {
        "id": "101300",
        "level": 2,
        "name": {
          "local": "Bukidnon",
          "en": "Bukidnon",
          "slug": "bukidnon-101300"
        }
      },
      {
        "id": "101306",
        "level": 3,
        "name": {
          "local": "Kadingilan",
          "en": "Kadingilan",
          "slug": "kadingilan-101306"
        }
      }
    ],
    "children_count": {},
    "zip_codes": [
      "8713"
    ],
    "geo": {
      "lat": "7.5208",
      "lon": "124.9103"
    },
    "metadata": {},
    "source": {}
  },
  {
    "id": "101306003",
    "level": 4,
    "level_name": {
      "local": "Barangay",
      "en": "Barangay"
    },
    "name": {
      "local": "Balaoro",
      "en": "Balaoro",
      "slug": "balaoro-101306003"
    },
    "code": {
      "id": "101306003",
      "iso": null
    },
    "parent": {
      "id": "101306",
      "level": 3,
      "name": {
        "local": "Kadingilan",
        "en": "Kadingilan",
        "slug": "kadingilan-101306"
      }
    },
    "ancestors": [
      {
        "id": "R10",
        "level": 1,
        "name": {
          "local": "Northern Mindanao",
          "en": "Northern Mindanao",
          "slug": "northern-mindanao-R10"
        }
      },
      {
        "id": "101300",
        "level": 2,
        "name": {
          "local": "Bukidnon",
          "en": "Bukidnon",
          "slug": "bukidnon-101300"
        }
      },
      {
        "id": "101306",
        "level": 3,
        "name": {
          "local": "Kadingilan",
          "en": "Kadingilan",
          "slug": "kadingilan-101306"
        }
      }
    ],
    "children_count": {},
    "zip_codes": [
      "8713"
    ],
    "geo": {
      "lat": "7.6",
      "lon": "124.917"
    },
    "metadata": {},
    "source": {}
  },
  {
    "id": "101306004",
    "level": 4,
    "level_name": {
      "local": "Barangay",
      "en": "Barangay"
    },
    "name": {
      "local": "Baroy",
      "en": "Baroy",
      "slug": "baroy-101306004"
    },
    "code": {
      "id": "101306004",
      "iso": null
    },
    "parent": {
      "id": "101306",
      "level": 3,
      "name": {
        "local": "Kadingilan",
        "en": "Kadingilan",
        "slug": "kadingilan-101306"
      }
    },
    "ancestors": [
      {
        "id": "R10",
        "level": 1,
        "name": {
          "local": "Northern Mindanao",
          "en": "Northern Mindanao",
          "slug": "northern-mindanao-R10"
        }
      },
      {
        "id": "101300",
        "level": 2,
        "name": {
          "local": "Bukidnon",
          "en": "Bukidnon",
          "slug": "bukidnon-101300"
        }
      },
      {
        "id": "101306",
        "level": 3,
        "name": {
          "local": "Kadingilan",
          "en": "Kadingilan",
          "slug": "kadingilan-101306"
        }
      }
    ],
    "children_count": {},
    "zip_codes": [
      "8713"
    ],
    "geo": {
      "lat": "8.03",
      "lon": "123.78"
    },
    "metadata": {},
    "source": {}
  },
  {
    "id": "101306005",
    "level": 4,
    "level_name": {
      "local": "Barangay",
      "en": "Barangay"
    },
    "name": {
      "local": "Cabadiangan",
      "en": "Cabadiangan",
      "slug": "cabadiangan-101306005"
    },
    "code": {
      "id": "101306005",
      "iso": null
    },
    "parent": {
      "id": "101306",
      "level": 3,
      "name": {
        "local": "Kadingilan",
        "en": "Kadingilan",
        "slug": "kadingilan-101306"
      }
    },
    "ancestors": [
      {
        "id": "R10",
        "level": 1,
        "name": {
          "local": "Northern Mindanao",
          "en": "Northern Mindanao",
          "slug": "northern-mindanao-R10"
        }
      },
      {
        "id": "101300",
        "level": 2,
        "name": {
          "local": "Bukidnon",
          "en": "Bukidnon",
          "slug": "bukidnon-101300"
        }
      },
      {
        "id": "101306",
        "level": 3,
        "name": {
          "local": "Kadingilan",
          "en": "Kadingilan",
          "slug": "kadingilan-101306"
        }
      }
    ],
    "children_count": {},
    "zip_codes": [
      "8713"
    ],
    "geo": {
      "lat": "9.6406",
      "lon": "124.0493"
    },
    "metadata": {},
    "source": {}
  },
  {
    "id": "101306006",
    "level": 4,
    "level_name": {
      "local": "Barangay",
      "en": "Barangay"
    },
    "name": {
      "local": "Husayan",
      "en": "Husayan",
      "slug": "husayan-101306006"
    },
    "code": {
      "id": "101306006",
      "iso": null
    },
    "parent": {
      "id": "101306",
      "level": 3,
      "name": {
        "local": "Kadingilan",
        "en": "Kadingilan",
        "slug": "kadingilan-101306"
      }
    },
    "ancestors": [
      {
        "id": "R10",
        "level": 1,
        "name": {
          "local": "Northern Mindanao",
          "en": "Northern Mindanao",
          "slug": "northern-mindanao-R10"
        }
      },
      {
        "id": "101300",
        "level": 2,
        "name": {
          "local": "Bukidnon",
          "en": "Bukidnon",
          "slug": "bukidnon-101300"
        }
      },
      {
        "id": "101306",
        "level": 3,
        "name": {
          "local": "Kadingilan",
          "en": "Kadingilan",
          "slug": "kadingilan-101306"
        }
      }
    ],
    "children_count": {},
    "zip_codes": [
      "8713"
    ],
    "geo": {
      "lat": "7.6",
      "lon": "124.917"
    },
    "metadata": {},
    "source": {}
  },
  {
    "id": "101306007",
    "level": 4,
    "level_name": {
      "local": "Barangay",
      "en": "Barangay"
    },
    "name": {
      "local": "Kibalagon",
      "en": "Kibalagon",
      "slug": "kibalagon-101306007"
    },
    "code": {
      "id": "101306007",
      "iso": null
    },
    "parent": {
      "id": "101306",
      "level": 3,
      "name": {
        "local": "Kadingilan",
        "en": "Kadingilan",
        "slug": "kadingilan-101306"
      }
    },
    "ancestors": [
      {
        "id": "R10",
        "level": 1,
        "name": {
          "local": "Northern Mindanao",
          "en": "Northern Mindanao",
          "slug": "northern-mindanao-R10"
        }
      },
      {
        "id": "101300",
        "level": 2,
        "name": {
          "local": "Bukidnon",
          "en": "Bukidnon",
          "slug": "bukidnon-101300"
        }
      },
      {
        "id": "101306",
        "level": 3,
        "name": {
          "local": "Kadingilan",
          "en": "Kadingilan",
          "slug": "kadingilan-101306"
        }
      }
    ],
    "children_count": {},
    "zip_codes": [
      "8713"
    ],
    "geo": {
      "lat": "7.6",
      "lon": "124.917"
    },
    "metadata": {},
    "source": {}
  },
  {
    "id": "101306017",
    "level": 4,
    "level_name": {
      "local": "Barangay",
      "en": "Barangay"
    },
    "name": {
      "local": "Kibogtok",
      "en": "Kibogtok",
      "slug": "kibogtok-101306017"
    },
    "code": {
      "id": "101306017",
      "iso": null
    },
    "parent": {
      "id": "101306",
      "level": 3,
      "name": {
        "local": "Kadingilan",
        "en": "Kadingilan",
        "slug": "kadingilan-101306"
      }
    },
    "ancestors": [
      {
        "id": "R10",
        "level": 1,
        "name": {
          "local": "Northern Mindanao",
          "en": "Northern Mindanao",
          "slug": "northern-mindanao-R10"
        }
      },
      {
        "id": "101300",
        "level": 2,
        "name": {
          "local": "Bukidnon",
          "en": "Bukidnon",
          "slug": "bukidnon-101300"
        }
      },
      {
        "id": "101306",
        "level": 3,
        "name": {
          "local": "Kadingilan",
          "en": "Kadingilan",
          "slug": "kadingilan-101306"
        }
      }
    ],
    "children_count": {},
    "zip_codes": [
      "8713"
    ],
    "geo": {
      "lat": "7.6",
      "lon": "124.917"
    },
    "metadata": {},
    "source": {}
  },
  {
    "id": "101306008",
    "level": 4,
    "level_name": {
      "local": "Barangay",
      "en": "Barangay"
    },
    "name": {
      "local": "Mabuhay",
      "en": "Mabuhay",
      "slug": "mabuhay-101306008"
    },
    "code": {
      "id": "101306008",
      "iso": null
    },
    "parent": {
      "id": "101306",
      "level": 3,
      "name": {
        "local": "Kadingilan",
        "en": "Kadingilan",
        "slug": "kadingilan-101306"
      }
    },
    "ancestors": [
      {
        "id": "R10",
        "level": 1,
        "name": {
          "local": "Northern Mindanao",
          "en": "Northern Mindanao",
          "slug": "northern-mindanao-R10"
        }
      },
      {
        "id": "101300",
        "level": 2,
        "name": {
          "local": "Bukidnon",
          "en": "Bukidnon",
          "slug": "bukidnon-101300"
        }
      },
      {
        "id": "101306",
        "level": 3,
        "name": {
          "local": "Kadingilan",
          "en": "Kadingilan",
          "slug": "kadingilan-101306"
        }
      }
    ],
    "children_count": {},
    "zip_codes": [
      "8713"
    ],
    "geo": {
      "lat": "8.2639",
      "lon": "124.6872"
    },
    "metadata": {},
    "source": {}
  },
  {
    "id": "101306009",
    "level": 4,
    "level_name": {
      "local": "Barangay",
      "en": "Barangay"
    },
    "name": {
      "local": "Malinao",
      "en": "Malinao",
      "slug": "malinao-101306009"
    },
    "code": {
      "id": "101306009",
      "iso": null
    },
    "parent": {
      "id": "101306",
      "level": 3,
      "name": {
        "local": "Kadingilan",
        "en": "Kadingilan",
        "slug": "kadingilan-101306"
      }
    },
    "ancestors": [
      {
        "id": "R10",
        "level": 1,
        "name": {
          "local": "Northern Mindanao",
          "en": "Northern Mindanao",
          "slug": "northern-mindanao-R10"
        }
      },
      {
        "id": "101300",
        "level": 2,
        "name": {
          "local": "Bukidnon",
          "en": "Bukidnon",
          "slug": "bukidnon-101300"
        }
      },
      {
        "id": "101306",
        "level": 3,
        "name": {
          "local": "Kadingilan",
          "en": "Kadingilan",
          "slug": "kadingilan-101306"
        }
      }
    ],
    "children_count": {},
    "zip_codes": [
      "8713"
    ],
    "geo": {
      "lat": "8.2414",
      "lon": "124.5814"
    },
    "metadata": {},
    "source": {}
  },
  {
    "id": "101306010",
    "level": 4,
    "level_name": {
      "local": "Barangay",
      "en": "Barangay"
    },
    "name": {
      "local": "Matampay",
      "en": "Matampay",
      "slug": "matampay-101306010"
    },
    "code": {
      "id": "101306010",
      "iso": null
    },
    "parent": {
      "id": "101306",
      "level": 3,
      "name": {
        "local": "Kadingilan",
        "en": "Kadingilan",
        "slug": "kadingilan-101306"
      }
    },
    "ancestors": [
      {
        "id": "R10",
        "level": 1,
        "name": {
          "local": "Northern Mindanao",
          "en": "Northern Mindanao",
          "slug": "northern-mindanao-R10"
        }
      },
      {
        "id": "101300",
        "level": 2,
        "name": {
          "local": "Bukidnon",
          "en": "Bukidnon",
          "slug": "bukidnon-101300"
        }
      },
      {
        "id": "101306",
        "level": 3,
        "name": {
          "local": "Kadingilan",
          "en": "Kadingilan",
          "slug": "kadingilan-101306"
        }
      }
    ],
    "children_count": {},
    "zip_codes": [
      "8713"
    ],
    "geo": {
      "lat": "8.0064",
      "lon": "124.2753"
    },
    "metadata": {},
    "source": {}
  },
  {
    "id": "101306012",
    "level": 4,
    "level_name": {
      "local": "Barangay",
      "en": "Barangay"
    },
    "name": {
      "local": "Pay-as",
      "en": "Pay-as",
      "slug": "pay-as-101306012"
    },
    "code": {
      "id": "101306012",
      "iso": null
    },
    "parent": {
      "id": "101306",
      "level": 3,
      "name": {
        "local": "Kadingilan",
        "en": "Kadingilan",
        "slug": "kadingilan-101306"
      }
    },
    "ancestors": [
      {
        "id": "R10",
        "level": 1,
        "name": {
          "local": "Northern Mindanao",
          "en": "Northern Mindanao",
          "slug": "northern-mindanao-R10"
        }
      },
      {
        "id": "101300",
        "level": 2,
        "name": {
          "local": "Bukidnon",
          "en": "Bukidnon",
          "slug": "bukidnon-101300"
        }
      },
      {
        "id": "101306",
        "level": 3,
        "name": {
          "local": "Kadingilan",
          "en": "Kadingilan",
          "slug": "kadingilan-101306"
        }
      }
    ],
    "children_count": {},
    "zip_codes": [
      "8713"
    ],
    "geo": {
      "lat": "15.9703",
      "lon": "120.4242"
    },
    "metadata": {},
    "source": {}
  },
  {
    "id": "101306013",
    "level": 4,
    "level_name": {
      "local": "Barangay",
      "en": "Barangay"
    },
    "name": {
      "local": "Pinamanguhan",
      "en": "Pinamanguhan",
      "slug": "pinamanguhan-101306013"
    },
    "code": {
      "id": "101306013",
      "iso": null
    },
    "parent": {
      "id": "101306",
      "level": 3,
      "name": {
        "local": "Kadingilan",
        "en": "Kadingilan",
        "slug": "kadingilan-101306"
      }
    },
    "ancestors": [
      {
        "id": "R10",
        "level": 1,
        "name": {
          "local": "Northern Mindanao",
          "en": "Northern Mindanao",
          "slug": "northern-mindanao-R10"
        }
      },
      {
        "id": "101300",
        "level": 2,
        "name": {
          "local": "Bukidnon",
          "en": "Bukidnon",
          "slug": "bukidnon-101300"
        }
      },
      {
        "id": "101306",
        "level": 3,
        "name": {
          "local": "Kadingilan",
          "en": "Kadingilan",
          "slug": "kadingilan-101306"
        }
      }
    ],
    "children_count": {},
    "zip_codes": [
      "8713"
    ],
    "geo": {
      "lat": "7.6",
      "lon": "124.917"
    },
    "metadata": {},
    "source": {}
  },
  {
    "id": "101306014",
    "level": 4,
    "level_name": {
      "local": "Barangay",
      "en": "Barangay"
    },
    "name": {
      "local": "Poblacion",
      "en": "Poblacion",
      "slug": "poblacion-101306014"
    },
    "code": {
      "id": "101306014",
      "iso": null
    },
    "parent": {
      "id": "101306",
      "level": 3,
      "name": {
        "local": "Kadingilan",
        "en": "Kadingilan",
        "slug": "kadingilan-101306"
      }
    },
    "ancestors": [
      {
        "id": "R10",
        "level": 1,
        "name": {
          "local": "Northern Mindanao",
          "en": "Northern Mindanao",
          "slug": "northern-mindanao-R10"
        }
      },
      {
        "id": "101300",
        "level": 2,
        "name": {
          "local": "Bukidnon",
          "en": "Bukidnon",
          "slug": "bukidnon-101300"
        }
      },
      {
        "id": "101306",
        "level": 3,
        "name": {
          "local": "Kadingilan",
          "en": "Kadingilan",
          "slug": "kadingilan-101306"
        }
      }
    ],
    "children_count": {},
    "zip_codes": [
      "8713"
    ],
    "geo": {
      "lat": "14.33",
      "lon": "121.08"
    },
    "metadata": {},
    "source": {}
  },
  {
    "id": "101306015",
    "level": 4,
    "level_name": {
      "local": "Barangay",
      "en": "Barangay"
    },
    "name": {
      "local": "Salvacion",
      "en": "Salvacion",
      "slug": "salvacion-101306015"
    },
    "code": {
      "id": "101306015",
      "iso": null
    },
    "parent": {
      "id": "101306",
      "level": 3,
      "name": {
        "local": "Kadingilan",
        "en": "Kadingilan",
        "slug": "kadingilan-101306"
      }
    },
    "ancestors": [
      {
        "id": "R10",
        "level": 1,
        "name": {
          "local": "Northern Mindanao",
          "en": "Northern Mindanao",
          "slug": "northern-mindanao-R10"
        }
      },
      {
        "id": "101300",
        "level": 2,
        "name": {
          "local": "Bukidnon",
          "en": "Bukidnon",
          "slug": "bukidnon-101300"
        }
      },
      {
        "id": "101306",
        "level": 3,
        "name": {
          "local": "Kadingilan",
          "en": "Kadingilan",
          "slug": "kadingilan-101306"
        }
      }
    ],
    "children_count": {},
    "zip_codes": [
      "8713"
    ],
    "geo": {
      "lat": "14.2927",
      "lon": "122.6281"
    },
    "metadata": {},
    "source": {}
  },
  {
    "id": "101306016",
    "level": 4,
    "level_name": {
      "local": "Barangay",
      "en": "Barangay"
    },
    "name": {
      "local": "San Andres",
      "en": "San Andres",
      "slug": "san-andres-101306016"
    },
    "code": {
      "id": "101306016",
      "iso": null
    },
    "parent": {
      "id": "101306",
      "level": 3,
      "name": {
        "local": "Kadingilan",
        "en": "Kadingilan",
        "slug": "kadingilan-101306"
      }
    },
    "ancestors": [
      {
        "id": "R10",
        "level": 1,
        "name": {
          "local": "Northern Mindanao",
          "en": "Northern Mindanao",
          "slug": "northern-mindanao-R10"
        }
      },
      {
        "id": "101300",
        "level": 2,
        "name": {
          "local": "Bukidnon",
          "en": "Bukidnon",
          "slug": "bukidnon-101300"
        }
      },
      {
        "id": "101306",
        "level": 3,
        "name": {
          "local": "Kadingilan",
          "en": "Kadingilan",
          "slug": "kadingilan-101306"
        }
      }
    ],
    "children_count": {},
    "zip_codes": [
      "8713"
    ],
    "geo": {
      "lat": "14.5739",
      "lon": "121.0039"
    },
    "metadata": {},
    "source": {}
  },
  {
    "id": "101306011",
    "level": 4,
    "level_name": {
      "local": "Barangay",
      "en": "Barangay"
    },
    "name": {
      "local": "Sibonga",
      "en": "Sibonga",
      "slug": "sibonga-101306011"
    },
    "code": {
      "id": "101306011",
      "iso": null
    },
    "parent": {
      "id": "101306",
      "level": 3,
      "name": {
        "local": "Kadingilan",
        "en": "Kadingilan",
        "slug": "kadingilan-101306"
      }
    },
    "ancestors": [
      {
        "id": "R10",
        "level": 1,
        "name": {
          "local": "Northern Mindanao",
          "en": "Northern Mindanao",
          "slug": "northern-mindanao-R10"
        }
      },
      {
        "id": "101300",
        "level": 2,
        "name": {
          "local": "Bukidnon",
          "en": "Bukidnon",
          "slug": "bukidnon-101300"
        }
      },
      {
        "id": "101306",
        "level": 3,
        "name": {
          "local": "Kadingilan",
          "en": "Kadingilan",
          "slug": "kadingilan-101306"
        }
      }
    ],
    "children_count": {},
    "zip_codes": [
      "8713"
    ],
    "geo": {
      "lat": "10.03",
      "lon": "123.57"
    },
    "metadata": {},
    "source": {}
  }
]