[
  {
    "id": "097312001",
    "level": 4,
    "level_name": {
      "local": "Barangay",
      "en": "Barangay"
    },
    "name": {
      "local": "Bagalupa",
      "en": "Bagalupa",
      "slug": "bagalupa-097312001"
    },
    "code": {
      "id": "097312001",
      "iso": null
    },
    "parent": {
      "id": "097312",
      "level": 3,
      "name": {
        "local": "Labangan",
        "en": "Labangan",
        "slug": "labangan-097312"
      }
    },
    "ancestors": [
      {
        "id": "R09",
        "level": 1,
        "name": {
          "local": "Zamboanga Peninsula",
          "en": "Zamboanga Peninsula",
          "slug": "zamboanga-peninsula-R09"
        }
      },
      {
        "id": "097300",
        "level": 2,
        "name": {
          "local": "Zamboanga del Sur",
          "en": "Zamboanga del Sur",
          "slug": "zamboanga-del-sur-097300"
        }
      },
      {
        "id": "097312",
        "level": 3,
        "name": {
          "local": "Labangan",
          "en": "Labangan",
          "slug": "labangan-097312"
        }
      }
    ],
    "children_count": {},
    "zip_codes": [
      "7017"
    ],
    "geo": {
      "lat": "7.867",
      "lon": "123.517"
    },
    "metadata": {},
    "source": {}
  },
  {
    "id": "097312003",
    "level": 4,
    "level_name": {
      "local": "Barangay",
      "en": "Barangay"
    },
    "name": {
      "local": "Balimbingan (West Luya)",
      "en": "Balimbingan (West Luya)",
      "slug": "balimbingan-west-luya-097312003"
    },
    "code": {
      "id": "097312003",
      "iso": null
    },
    "parent": {
      "id": "097312",
      "level": 3,
      "name": {
        "local": "Labangan",
        "en": "Labangan",
        "slug": "labangan-097312"
      }
    },
    "ancestors": [
      {
        "id": "R09",
        "level": 1,
        "name": {
          "local": "Zamboanga Peninsula",
          "en": "Zamboanga Peninsula",
          "slug": "zamboanga-peninsula-R09"
        }
      },
      {
        "id": "097300",
        "level": 2,
        "name": {
          "local": "Zamboanga del Sur",
          "en": "Zamboanga del Sur",
          "slug": "zamboanga-del-sur-097300"
        }
      },
      {
        "id": "097312",
        "level": 3,
        "name": {
          "local": "Labangan",
          "en": "Labangan",
          "slug": "labangan-097312"
        }
      }
    ],
    "children_count": {},
    "zip_codes": [
      "7017"
    ],
    "geo": {
      "lat": "7.8912",
      "lon": "123.5317"
    },
    "metadata": {},
    "source": {}
  },
  {
    "id": "097312005",
    "level": 4,
    "level_name": {
      "local": "Barangay",
      "en": "Barangay"
    },
    "name": {
      "local": "Binayan",
      "en": "Binayan",
      "slug": "binayan-097312005"
    },
    "code": {
      "id": "097312005",
      "iso": null
    },
    "parent": {
      "id": "097312",
      "level": 3,
      "name": {
        "local": "Labangan",
        "en": "Labangan",
        "slug": "labangan-097312"
      }
    },
    "ancestors": [
      {
        "id": "R09",
        "level": 1,
        "name": {
          "local": "Zamboanga Peninsula",
          "en": "Zamboanga Peninsula",
          "slug": "zamboanga-peninsula-R09"
        }
      },
      {
        "id": "097300",
        "level": 2,
        "name": {
          "local": "Zamboanga del Sur",
          "en": "Zamboanga del Sur",
          "slug": "zamboanga-del-sur-097300"
        }
      },
      {
        "id": "097312",
        "level": 3,
        "name": {
          "local": "Labangan",
          "en": "Labangan",
          "slug": "labangan-097312"
        }
      }
    ],
    "children_count": {},
    "zip_codes": [
      "7017"
    ],
    "geo": {
      "lat": "7.9127",
      "lon": "123.4394"
    },
    "metadata": {},
    "source": {}
  },
  {
    "id": "097312006",
    "level": 4,
    "level_name": {
      "local": "Barangay",
      "en": "Barangay"
    },
    "name": {
      "local": "Bokong",
      "en": "Bokong",
      "slug": "bokong-097312006"
    },
    "code": {
      "id": "097312006",
      "iso": null
    },
    "parent": {
      "id": "097312",
      "level": 3,
      "name": {
        "local": "Labangan",
        "en": "Labangan",
        "slug": "labangan-097312"
      }
    },
    "ancestors": [
      {
        "id": "R09",
        "level": 1,
        "name": {
          "local": "Zamboanga Peninsula",
          "en": "Zamboanga Peninsula",
          "slug": "zamboanga-peninsula-R09"
        }
      },
      {
        "id": "097300",
        "level": 2,
        "name": {
          "local": "Zamboanga del Sur",
          "en": "Zamboanga del Sur",
          "slug": "zamboanga-del-sur-097300"
        }
      },
      {
        "id": "097312",
        "level": 3,
        "name": {
          "local": "Labangan",
          "en": "Labangan",
          "slug": "labangan-097312"
        }
      }
    ],
    "children_count": {},
    "zip_codes": [
      "7017"
    ],
    "geo": {
      "lat": "7.867",
      "lon": "123.517"
    },
    "metadata": {},
    "source": {}
  },
  {
    "id": "097312007",
    "level": 4,
    "level_name": {
      "local": "Barangay",
      "en": "Barangay"
    },
    "name": {
      "local": "Bulanit",
      "en": "Bulanit",
      "slug": "bulanit-097312007"
    },
    "code": {
      "id": "097312007",
      "iso": null
    },
    "parent": {
      "id": "097312",
      "level": 3,
      "name": {
        "local": "Labangan",
        "en": "Labangan",
        "slug": "labangan-097312"
      }
    },
    "ancestors": [
      {
        "id": "R09",
        "level": 1,
        "name": {
          "local": "Zamboanga Peninsula",
          "en": "Zamboanga Peninsula",
          "slug": "zamboanga-peninsula-R09"
        }
      },
      {
        "id": "097300",
        "level": 2,
        "name": {
          "local": "Zamboanga del Sur",
          "en": "Zamboanga del Sur",
          "slug": "zamboanga-del-sur-097300"
        }
      },
      {
        "id": "097312",
        "level": 3,
        "name": {
          "local": "Labangan",
          "en": "Labangan",
          "slug": "labangan-097312"
        }
      }
    ],
    "children_count": {},
    "zip_codes": [
      "7017"
    ],
    "geo": {
      "lat": "7.84",
      "lon": "123.4803"
    },
    "metadata": {},
    "source": {}
  },
  {
    "id": "097312008",
    "level": 4,
    "level_name": {
      "local": "Barangay",
      "en": "Barangay"
    },
    "name": {
      "local": "Cogonan",
      "en": "Cogonan",
      "slug": "cogonan-097312008"
    },
    "code": {
      "id": "097312008",
      "iso": null
    },
    "parent": {
      "id": "097312",
      "level": 3,
      "name": {
        "local": "Labangan",
        "en": "Labangan",
        "slug": "labangan-097312"
      }
    },
    "ancestors": [
      {
        "id": "R09",
        "level": 1,
        "name": {
          "local": "Zamboanga Peninsula",
          "en": "Zamboanga Peninsula",
          "slug": "zamboanga-peninsula-R09"
        }
      },
      {
        "id": "097300",
        "level": 2,
        "name": {
          "local": "Zamboanga del Sur",
          "en": "Zamboanga del Sur",
          "slug": "zamboanga-del-sur-097300"
        }
      },
      {
        "id": "097312",
        "level": 3,
        "name": {
          "local": "Labangan",
          "en": "Labangan",
          "slug": "labangan-097312"
        }
      }
    ],
    "children_count": {},
    "zip_codes": [
      "7017"
    ],
    "geo": {
      "lat": "14.0606",
      "lon": "120.6588"
    },
    "metadata": {},
    "source": {}
  },
  {
    "id": "097312026",
    "level": 4,
    "level_name": {
      "local": "Barangay",
      "en": "Barangay"
    },
    "name": {
      "local": "Combo",
      "en": "Combo",
      "slug": "combo-097312026"
    },
    "code": {
      "id": "097312026",
      "iso": null
    },
    "parent": {
      "id": "097312",
      "level": 3,
      "name": {
        "local": "Labangan",
        "en": "Labangan",
        "slug": "labangan-097312"
      }
    },
    "ancestors": [
      {
        "id": "R09",
        "level": 1,
        "name": {
          "local": "Zamboanga Peninsula",
          "en": "Zamboanga Peninsula",
          "slug": "zamboanga-peninsula-R09"
        }
      },
      {
        "id": "097300",
        "level": 2,
        "name": {
          "local": "Zamboanga del Sur",
          "en": "Zamboanga del Sur",
          "slug": "zamboanga-del-sur-097300"
        }
      },
      {
        "id": "097312",
        "level": 3,
        "name": {
          "local": "Labangan",
          "en": "Labangan",
          "slug": "labangan-097312"
        }
      }
    ],
    "children_count": {},
    "zip_codes": [
      "7017"
    ],
    "geo": {
      "lat": "7.867",
      "lon": "123.517"
    },
    "metadata": {},
    "source": {}
  },
  {
    "id": "097312009",
    "level": 4,
    "level_name": {
      "local": "Barangay",
      "en": "Barangay"
    },
    "name": {
      "local": "Dalapang",
      "en": "Dalapang",
      "slug": "dalapang-097312009"
    },
    "code": {
      "id": "097312009",
      "iso": null
    },
    "parent": {
      "id": "097312",
      "level": 3,
      "name": {
        "local": "Labangan",
        "en": "Labangan",
        "slug": "labangan-097312"
      }
    },
    "ancestors": [
      {
        "id": "R09",
        "level": 1,
        "name": {
          "local": "Zamboanga Peninsula",
          "en": "Zamboanga Peninsula",
          "slug": "zamboanga-peninsula-R09"
        }
      },
      {
        "id": "097300",
        "level": 2,
        "name": {
          "local": "Zamboanga del Sur",
          "en": "Zamboanga del Sur",
          "slug": "zamboanga-del-sur-097300"
        }
      },
      {
        "id": "097312",
        "level": 3,
        "name": {
          "local": "Labangan",
          "en": "Labangan",
          "slug": "labangan-097312"
        }
      }
    ],
    "children_count": {},
    "zip_codes": [
      "7017"
    ],
    "geo": {
      "lat": "7.7272",
      "lon": "123.2867"
    },
    "metadata": {},
    "source": {}
  },
  {
    "id": "097312027",
    "level": 4,
    "level_name": {
      "local": "Barangay",
      "en": "Barangay"
    },
    "name": {
      "local": "Dimasangca",
      "en": "Dimasangca",
      "slug": "dimasangca-097312027"
    },
    "code": {
      "id": "097312027",
      "iso": null
    },
    "parent": {
      "id": "097312",
      "level": 3,
      "name": {
        "local": "Labangan",
        "en": "Labangan",
        "slug": "labangan-097312"
      }
    },
    "ancestors": [
      {
        "id": "R09",
        "level": 1,
        "name": {
          "local": "Zamboanga Peninsula",
          "en": "Zamboanga Peninsula",
          "slug": "zamboanga-peninsula-R09"
        }
      },
      {
        "id": "097300",
        "level": 2,
        "name": {
          "local": "Zamboanga del Sur",
          "en": "Zamboanga del Sur",
          "slug": "zamboanga-del-sur-097300"
        }
      },
      {
        "id": "097312",
        "level": 3,
        "name": {
          "local": "Labangan",
          "en": "Labangan",
          "slug": "labangan-097312"
        }
      }
    ],
    "children_count": {},
    "zip_codes": [
      "7017"
    ],
    "geo": {
      "lat": "7.867",
      "lon": "123.517"
    },
    "metadata": {},
    "source": {}
  },
  {
    "id": "097312010",
    "level": 4,
    "level_name": {
      "local": "Barangay",
      "en": "Barangay"
    },
    "name": {
      "local": "Dipaya",
      "en": "Dipaya",
      "slug": "dipaya-097312010"
    },
    "code": {
      "id": "097312010",
      "iso": null
    },
    "parent": {
      "id": "097312",
      "level": 3,
      "name": {
        "local": "Labangan",
        "en": "Labangan",
        "slug": "labangan-097312"
      }
    },
    "ancestors": [
      {
        "id": "R09",
        "level": 1,
        "name": {
          "local": "Zamboanga Peninsula",
          "en": "Zamboanga Peninsula",
          "slug": "zamboanga-peninsula-R09"
        }
      },
      {
        "id": "097300",
        "level": 2,
        "name": {
          "local": "Zamboanga del Sur",
          "en": "Zamboanga del Sur",
          "slug": "zamboanga-del-sur-097300"
        }
      },
      {
        "id": "097312",
        "level": 3,
        "name": {
          "local": "Labangan",
          "en": "Labangan",
          "slug": "labangan-097312"
        }
      }
    ],
    "children_count": {},
    "zip_codes": [
      "7017"
    ],
    "geo": {
      "lat": "7.867",
      "lon": "123.517"
    },
    "metadata": {},
    "source": {}
  },
  {
    "id": "097312011",
    "level": 4,
    "level_name": {
      "local": "Barangay",
      "en": "Barangay"
    },
    "name": {
      "local": "Langapod",
      "en": "Langapod",
      "slug": "langapod-097312011"
    },
    "code": {
      "id": "097312011",
      "iso": null
    },
    "parent": {
      "id": "097312",
      "level": 3,
      "name": {
        "local": "Labangan",
        "en": "Labangan",
        "slug": "labangan-097312"
      }
    },
    "ancestors": [
      {
        "id": "R09",
        "level": 1,
        "name": {
          "local": "Zamboanga Peninsula",
          "en": "Zamboanga Peninsula",
          "slug": "zamboanga-peninsula-R09"
        }
      },
      {
        "id": "097300",
        "level": 2,
        "name": {
          "local": "Zamboanga del Sur",
          "en": "Zamboanga del Sur",
          "slug": "zamboanga-del-sur-097300"
        }
      },
      {
        "id": "097312",
        "level": 3,
        "name": {
          "local": "Labangan",
          "en": "Labangan",
          "slug": "labangan-097312"
        }
      }
    ],
    "children_count": {},
    "zip_codes": [
      "7017"
    ],
    "geo": {
      "lat": "7.867",
      "lon": "123.517"
    },
    "metadata": {},
    "source": {}
  },
  {
    "id": "097312012",
    "level": 4,
    "level_name": {
      "local": "Barangay",
      "en": "Barangay"
    },
    "name": {
      "local": "Lantian",
      "en": "Lantian",
      "slug": "lantian-097312012"
    },
    "code": {
      "id": "097312012",
      "iso": null
    },
    "parent": {
      "id": "097312",
      "level": 3,
      "name": {
        "local": "Labangan",
        "en": "Labangan",
        "slug": "labangan-097312"
      }
    },
    "ancestors": [
      {
        "id": "R09",
        "level": 1,
        "name": {
          "local": "Zamboanga Peninsula",
          "en": "Zamboanga Peninsula",
          "slug": "zamboanga-peninsula-R09"
        }
      },
      {
        "id": "097300",
        "level": 2,
        "name": {
          "local": "Zamboanga del Sur",
          "en": "Zamboanga del Sur",
          "slug": "zamboanga-del-sur-097300"
        }
      },
      {
        "id": "097312",
        "level": 3,
        "name": {
          "local": "Labangan",
          "en": "Labangan",
          "slug": "labangan-097312"
        }
      }
    ],
    "children_count": {},
    "zip_codes": [
      "7017"
    ],
    "geo": {
      "lat": "7.8726",
      "lon": "123.5143"
    },
    "metadata": {},
    "source": {}
  },
  {
    "id": "097312013",
    "level": 4,
    "level_name": {
      "local": "Barangay",
      "en": "Barangay"
    },
    "name": {
      "local": "Lower Campo Islam (Pob.)",
      "en": "Lower Campo Islam (Pob.)",
      "slug": "lower-campo-islam-pob-097312013"
    },
    "code": {
      "id": "097312013",
      "iso": null
    },
    "parent": {
      "id": "097312",
      "level": 3,
      "name": {
        "local": "Labangan",
        "en": "Labangan",
        "slug": "labangan-097312"
      }
    },
    "ancestors": [
      {
        "id": "R09",
        "level": 1,
        "name": {
          "local": "Zamboanga Peninsula",
          "en": "Zamboanga Peninsula",
          "slug": "zamboanga-peninsula-R09"
        }
      },
      {
        "id": "097300",
        "level": 2,
        "name": {
          "local": "Zamboanga del Sur",
          "en": "Zamboanga del Sur",
          "slug": "zamboanga-del-sur-097300"
        }
      },
      {
        "id": "097312",
        "level": 3,
        "name": {
          "local": "Labangan",
          "en": "Labangan",
          "slug": "labangan-097312"
        }
      }
    ],
    "children_count": {},
    "zip_codes": [
      "7017"
    ],
    "geo": {
      "lat": "12.8993",
      "lon": "121.4572"
    },
    "metadata": {},
    "source": {}
  },
  {
    "id": "097312014",
    "level": 4,
    "level_name": {
      "local": "Barangay",
      "en": "Barangay"
    },
    "name": {
      "local": "Lower Pulacan",
      "en": "Lower Pulacan",
      "slug": "lower-pulacan-097312014"
    },
    "code": {
      "id": "097312014",
      "iso": null
    },
    "parent": {
      "id": "097312",
      "level": 3,
      "name": {
        "local": "Labangan",
        "en": "Labangan",
        "slug": "labangan-097312"
      }
    },
    "ancestors": [
      {
        "id": "R09",
        "level": 1,
        "name": {
          "local": "Zamboanga Peninsula",
          "en": "Zamboanga Peninsula",
          "slug": "zamboanga-peninsula-R09"
        }
      },
      {
        "id": "097300",
        "level": 2,
        "name": {
          "local": "Zamboanga del Sur",
          "en": "Zamboanga del Sur",
          "slug": "zamboanga-del-sur-097300"
        }
      },
      {
        "id": "097312",
        "level": 3,
        "name": {
          "local": "Labangan",
          "en": "Labangan",
          "slug": "labangan-097312"
        }
      }
    ],
    "children_count": {},
    "zip_codes": [
      "7017"
    ],
    "geo": {
      "lat": "12.8993",
      "lon": "121.4572"
    },
    "metadata": {},
    "source": {}
  },
  {
    "id": "097312028",
    "level": 4,
    "level_name": {
      "local": "Barangay",
      "en": "Barangay"
    },
    "name": {
      "local": "Lower Sang-an",
      "en": "Lower Sang-an",
      "slug": "lower-sang-an-097312028"
    },
    "code": {
      "id": "097312028",
      "iso": null
    },
    "parent": {
      "id": "097312",
      "level": 3,
      "name": {
        "local": "Labangan",
        "en": "Labangan",
        "slug": "labangan-097312"
      }
    },
    "ancestors": [
      {
        "id": "R09",
        "level": 1,
        "name": {
          "local": "Zamboanga Peninsula",
          "en": "Zamboanga Peninsula",
          "slug": "zamboanga-peninsula-R09"
        }
      },
      {
        "id": "097300",
        "level": 2,
        "name": {
          "local": "Zamboanga del Sur",
          "en": "Zamboanga del Sur",
          "slug": "zamboanga-del-sur-097300"
        }
      },
      {
        "id": "097312",
        "level": 3,
        "name": {
          "local": "Labangan",
          "en": "Labangan",
          "slug": "labangan-097312"
        }
      }
    ],
    "children_count": {},
    "zip_codes": [
      "7017"
    ],
    "geo": {
      "lat": "12.8993",
      "lon": "121.4572"
    },
    "metadata": {},
    "source": {}
  },
  {
    "id": "097312015",
    "level": 4,
    "level_name": {
      "local": "Barangay",
      "en": "Barangay"
    },
    "name": {
      "local": "New Labangan",
      "en": "New Labangan",
      "slug": "new-labangan-097312015"
    },
    "code": {
      "id": "097312015",
      "iso": null
    },
    "parent": {
      "id": "097312",
      "level": 3,
      "name": {
        "local": "Labangan",
        "en": "Labangan",
        "slug": "labangan-097312"
      }
    },
    "ancestors": [
      {
        "id": "R09",
        "level": 1,
        "name": {
          "local": "Zamboanga Peninsula",
          "en": "Zamboanga Peninsula",
          "slug": "zamboanga-peninsula-R09"
        }
      },
      {
        "id": "097300",
        "level": 2,
        "name": {
          "local": "Zamboanga del Sur",
          "en": "Zamboanga del Sur",
          "slug": "zamboanga-del-sur-097300"
        }
      },
      {
        "id": "097312",
        "level": 3,
        "name": {
          "local": "Labangan",
          "en": "Labangan",
          "slug": "labangan-097312"
        }
      }
    ],
    "children_count": {},
    "zip_codes": [
      "7017"
    ],
    "geo": {
      "lat": "7.8667",
      "lon": "123.5167"
    },
    "metadata": {},
    "source": {}
  },
  {
    "id": "097312016",
    "level": 4,
    "level_name": {
      "local": "Barangay",
      "en": "Barangay"
    },
    "name": {
      "local": "Noboran",
      "en": "Noboran",
      "slug": "noboran-097312016"
    },
    "code": {
      "id": "097312016",
      "iso": null
    },
    "parent": {
      "id": "097312",
      "level": 3,
      "name": {
        "local": "Labangan",
        "en": "Labangan",
        "slug": "labangan-097312"
      }
    },
    "ancestors": [
      {
        "id": "R09",
        "level": 1,
        "name": {
          "local": "Zamboanga Peninsula",
          "en": "Zamboanga Peninsula",
          "slug": "zamboanga-peninsula-R09"
        }
      },
      {
        "id": "097300",
        "level": 2,
        "name": {
          "local": "Zamboanga del Sur",
          "en": "Zamboanga del Sur",
          "slug": "zamboanga-del-sur-097300"
        }
      },
      {
        "id": "097312",
        "level": 3,
        "name": {
          "local": "Labangan",
          "en": "Labangan",
          "slug": "labangan-097312"
        }
      }
    ],
    "children_count": {},
    "zip_codes": [
      "7017"
    ],
    "geo": {
      "lat": "7.867",
      "lon": "123.517"
    },
    "metadata": {},
    "source": {}
  },
  {
    "id": "097312017",
    "level": 4,
    "level_name": {
      "local": "Barangay",
      "en": "Barangay"
    },
    "name": {
      "local": "Old Labangan",
      "en": "Old Labangan",
      "slug": "old-labangan-097312017"
    },
    "code": {
      "id": "097312017",
      "iso": null
    },
    "parent": {
      "id": "097312",
      "level": 3,
      "name": {
        "local": "Labangan",
        "en": "Labangan",
        "slug": "labangan-097312"
      }
    },
    "ancestors": [
      {
        "id": "R09",
        "level": 1,
        "name": {
          "local": "Zamboanga Peninsula",
          "en": "Zamboanga Peninsula",
          "slug": "zamboanga-peninsula-R09"
        }
      },
      {
        "id": "097300",
        "level": 2,
        "name": {
          "local": "Zamboanga del Sur",
          "en": "Zamboanga del Sur",
          "slug": "zamboanga-del-sur-097300"
        }
      },
      {
        "id": "097312",
        "level": 3,
        "name": {
          "local": "Labangan",
          "en": "Labangan",
          "slug": "labangan-097312"
        }
      }
    ],
    "children_count": {},
    "zip_codes": [
      "7017"
    ],
    "geo": {
      "lat": "7.8667",
      "lon": "123.5167"
    },
    "metadata": {},
    "source": {}
  },
  {
    "id": "097312019",
    "level": 4,
    "level_name": {
      "local": "Barangay",
      "en": "Barangay"
    },
    "name": {
      "local": "San Isidro",
      "en": "San Isidro",
      "slug": "san-isidro-097312019"
    },
    "code": {
      "id": "097312019",
      "iso": null
    },
    "parent": {
      "id": "097312",
      "level": 3,
      "name": {
        "local": "Labangan",
        "en": "Labangan",
        "slug": "labangan-097312"
      }
    },
    "ancestors": [
      {
        "id": "R09",
        "level": 1,
        "name": {
          "local": "Zamboanga Peninsula",
          "en": "Zamboanga Peninsula",
          "slug": "zamboanga-peninsula-R09"
        }
      },
      {
        "id": "097300",
        "level": 2,
        "name": {
          "local": "Zamboanga del Sur",
          "en": "Zamboanga del Sur",
          "slug": "zamboanga-del-sur-097300"
        }
      },
      {
        "id": "097312",
        "level": 3,
        "name": {
          "local": "Labangan",
          "en": "Labangan",
          "slug": "labangan-097312"
        }
      }
    ],
    "children_count": {},
    "zip_codes": [
      "7017"
    ],
    "geo": {
      "lat": "14.4685",
      "lon": "121.0118"
    },
    "metadata": {},
    "source": {}
  },
  {
    "id": "097312020",
    "level": 4,
    "level_name": {
      "local": "Barangay",
      "en": "Barangay"
    },
    "name": {
      "local": "Santa Cruz",
      "en": "Santa Cruz",
      "slug": "santa-cruz-097312020"
    },
    "code": {
      "id": "097312020",
      "iso": null
    },
    "parent": {
      "id": "097312",
      "level": 3,
      "name": {
        "local": "Labangan",
        "en": "Labangan",
        "slug": "labangan-097312"
      }
    },
    "ancestors": [
      {
        "id": "R09",
        "level": 1,
        "name": {
          "local": "Zamboanga Peninsula",
          "en": "Zamboanga Peninsula",
          "slug": "zamboanga-peninsula-R09"
        }
      },
      {
        "id": "097300",
        "level": 2,
        "name": {
          "local": "Zamboanga del Sur",
          "en": "Zamboanga del Sur",
          "slug": "zamboanga-del-sur-097300"
        }
      },
      {
        "id": "097312",
        "level": 3,
        "name": {
          "local": "Labangan",
          "en": "Labangan",
          "slug": "labangan-097312"
        }
      }
    ],
    "children_count": {},
    "zip_codes": [
      "7017"
    ],
    "geo": {
      "lat": "14.5998",
      "lon": "120.9802"
    },
    "metadata": {},
    "source": {}
  },
  {
    "id": "097312021",
    "level": 4,
    "level_name": {
      "local": "Barangay",
      "en": "Barangay"
    },
    "name": {
      "local": "Tapodoc",
      "en": "Tapodoc",
      "slug": "tapodoc-097312021"
    },
    "code": {
      "id": "097312021",
      "iso": null
    },
    "parent": {
      "id": "097312",
      "level": 3,
      "name": {
        "local": "Labangan",
        "en": "Labangan",
        "slug": "labangan-097312"
      }
    },
    "ancestors": [
      {
        "id": "R09",
        "level": 1,
        "name": {
          "local": "Zamboanga Peninsula",
          "en": "Zamboanga Peninsula",
          "slug": "zamboanga-peninsula-R09"
        }
      },
      {
        "id": "097300",
        "level": 2,
        "name": {
          "local": "Zamboanga del Sur",
          "en": "Zamboanga del Sur",
          "slug": "zamboanga-del-sur-097300"
        }
      },
      {
        "id": "097312",
        "level": 3,
        "name": {
          "local": "Labangan",
          "en": "Labangan",
          "slug": "labangan-097312"
        }
      }
    ],
    "children_count": {},
    "zip_codes": [
      "7017"
    ],
    "geo": {
      "lat": "7.867",
      "lon": "123.517"
    },
    "metadata": {},
    "source": {}
  },
  {
    "id": "097312022",
    "level": 4,
    "level_name": {
      "local": "Barangay",
      "en": "Barangay"
    },
    "name": {
      "local": "Tawagan Norte",
      "en": "Tawagan Norte",
      "slug": "tawagan-norte-097312022"
    },
    "code": {
      "id": "097312022",
      "iso": null
    },
    "parent": {
      "id": "097312",
      "level": 3,
      "name": {
        "local": "Labangan",
        "en": "Labangan",
        "slug": "labangan-097312"
      }
    },
    "ancestors": [
      {
        "id": "R09",
        "level": 1,
        "name": {
          "local": "Zamboanga Peninsula",
          "en": "Zamboanga Peninsula",
          "slug": "zamboanga-peninsula-R09"
        }
      },
      {
        "id": "097300",
        "level": 2,
        "name": {
          "local": "Zamboanga del Sur",
          "en": "Zamboanga del Sur",
          "slug": "zamboanga-del-sur-097300"
        }
      },
      {
        "id": "097312",
        "level": 3,
        "name": {
          "local": "Labangan",
          "en": "Labangan",
          "slug": "labangan-097312"
        }
      }
    ],
    "children_count": {},
    "zip_codes": [
      "7017"
    ],
    "geo": {
      "lat": "10.2738",
      "lon": "123.7563"
    },
    "metadata": {},
    "source": {}
  },
  {
    "id": "097312023",
    "level": 4,
    "level_name": {
      "local": "Barangay",
      "en": "Barangay"
    },
    "name": {
      "local": "Upper Campo Islam (Pob.)",
      "en": "Upper Campo Islam (Pob.)",
      "slug": "upper-campo-islam-pob-097312023"
    },
    "code": {
      "id": "097312023",
      "iso": null
    },
    "parent": {
      "id": "097312",
      "level": 3,
      "name": {
        "local": "Labangan",
        "en": "Labangan",
        "slug": "labangan-097312"
      }
    },
    "ancestors": [
      {
        "id": "R09",
        "level": 1,
        "name": {
          "local": "Zamboanga Peninsula",
          "en": "Zamboanga Peninsula",
          "slug": "zamboanga-peninsula-R09"
        }
      },
      {
        "id": "097300",
        "level": 2,
        "name": {
          "local": "Zamboanga del Sur",
          "en": "Zamboanga del Sur",
          "slug": "zamboanga-del-sur-097300"
        }
      },
      {
        "id": "097312",
        "level": 3,
        "name": {
          "local": "Labangan",
          "en": "Labangan",
          "slug": "labangan-097312"
        }
      }
    ],
    "children_count": {},
    "zip_codes": [
      "7017"
    ],
    "geo": {
      "lat": "7.867",
      "lon": "123.517"
    },
    "metadata": {},
    "source": {}
  },
  {
    "id": "097312024",
    "level": 4,
    "level_name": {
      "local": "Barangay",
      "en": "Barangay"
    },
    "name": {
      "local": "Upper Pulacan",
      "en": "Upper Pulacan",
      "slug": "upper-pulacan-097312024"
    },
    "code": {
      "id": "097312024",
      "iso": null
    },
    "parent": {
      "id": "097312",
      "level": 3,
      "name": {
        "local": "Labangan",
        "en": "Labangan",
        "slug": "labangan-097312"
      }
    },
    "ancestors": [
      {
        "id": "R09",
        "level": 1,
        "name": {
          "local": "Zamboanga Peninsula",
          "en": "Zamboanga Peninsula",
          "slug": "zamboanga-peninsula-R09"
        }
      },
      {
        "id": "097300",
        "level": 2,
        "name": {
          "local": "Zamboanga del Sur",
          "en": "Zamboanga del Sur",
          "slug": "zamboanga-del-sur-097300"
        }
      },
      {
        "id": "097312",
        "level": 3,
        "name": {
          "local": "Labangan",
          "en": "Labangan",
          "slug": "labangan-097312"
        }
      }
    ],
    "children_count": {},
    "zip_codes": [
      "7017"
    ],
    "geo": {
      "lat": "7.867",
      "lon": "123.517"
    },
    "metadata": {},
    "source": {}
  },
  {
    "id": "097312029",
    "level": 4,
    "level_name": {
      "local": "Barangay",
      "en": "Barangay"
    },
    "name": {
      "local": "Upper Sang-an",
      "en": "Upper Sang-an",
      "slug": "upper-sang-an-097312029"
    },
    "code": {
      "id": "097312029",
      "iso": null
    },
    "parent": {
      "id": "097312",
      "level": 3,
      "name": {
        "local": "Labangan",
        "en": "Labangan",
        "slug": "labangan-097312"
      }
    },
    "ancestors": [
      {
        "id": "R09",
        "level": 1,
        "name": {
          "local": "Zamboanga Peninsula",
          "en": "Zamboanga Peninsula",
          "slug": "zamboanga-peninsula-R09"
        }
      },
      {
        "id": "097300",
        "level": 2,
        "name": {
          "local": "Zamboanga del Sur",
          "en": "Zamboanga del Sur",
          "slug": "zamboanga-del-sur-097300"
        }
      },
      {
        "id": "097312",
        "level": 3,
        "name": {
          "local": "Labangan",
          "en": "Labangan",
          "slug": "labangan-097312"
        }
      }
    ],
    "children_count": {},
    "zip_codes": [
      "7017"
    ],
    "geo": {
      "lat": "17.8",
      "lon": "120.4833"
    },
    "metadata": {},
    "source": {}
  }
]